[
  {
    "codigo_localidad": "01",
    "nombre_localidad": "Usaquén",
    "lat": 4.7499,
    "lng": -74.0275,
    "mes": "Ene-Sep (2024vs2025)",
    "tipo": "Homicidios",
    "anio_2018": 25,
    "anio_2019": 20,
    "anio_2020": 39,
    "anio_2021": 29,
    "anio_2022": 22,
    "anio_2023": 24,
    "anio_2024": 31,
    "anio_2025": 36,
    "variacion_porcentaje": 16.13,
    "total_bogota": 875
  },
  {
    "codigo_localidad": "01",
    "nombre_localidad": "Usaquén",
    "lat": 4.7499,
    "lng": -74.0275,
    "mes": "Ene-Sep (2024vs2025)",
    "tipo": "Lesiones Personales",
    "anio_2018": 1002,
    "anio_2019": 712,
    "anio_2020": 482,
    "anio_2021": 786,
    "anio_2022": 607,
    "anio_2023": 560,
    "anio_2024": 599,
    "anio_2025": 594,
    "variacion_porcentaje": -0.83,
    "total_bogota": 15137
  },
  {
    "codigo_localidad": "01",
    "nombre_localidad": "Usaquén",
    "lat": 4.7499,
    "lng": -74.0275,
    "mes": "Ene-Sep (2024vs2025)",
    "tipo": "Hurto a Personas",
    "anio_2018": 6765,
    "anio_2019": 7907,
    "anio_2020": 4513,
    "anio_2021": 5541,
    "anio_2022": 6089,
    "anio_2023": 6477,
    "anio_2024": 6307,
    "anio_2025": 5993,
    "variacion_porcentaje": -4.98,
    "total_bogota": 100894
  },
  {
    "codigo_localidad": "01",
    "nombre_localidad": "Usaquén",
    "lat": 4.7499,
    "lng": -74.0275,
    "mes": "Ene-Sep (2024vs2025)",
    "tipo": "Hurto a Residencias",
    "anio_2018": 654,
    "anio_2019": 563,
    "anio_2020": 461,
    "anio_2021": 440,
    "anio_2022": 458,
    "anio_2023": 490,
    "anio_2024": 459,
    "anio_2025": 389,
    "variacion_porcentaje": -15.25,
    "total_bogota": 4701
  },
  {
    "codigo_localidad": "01",
    "nombre_localidad": "Usaquén",
    "lat": 4.7499,
    "lng": -74.0275,
    "mes": "Ene-Sep (2024vs2025)",
    "tipo": "Hurto de Automotores",
    "anio_2018": 121,
    "anio_2019": 75,
    "anio_2020": 81,
    "anio_2021": 101,
    "anio_2022": 103,
    "anio_2023": 76,
    "anio_2024": 103,
    "anio_2025": 46,
    "variacion_porcentaje": -55.34,
    "total_bogota": 2401
  },
  {
    "codigo_localidad": "01",
    "nombre_localidad": "Usaquén",
    "lat": 4.7499,
    "lng": -74.0275,
    "mes": "Ene-Sep (2024vs2025)",
    "tipo": "Hurto de Bicicletas",
    "anio_2018": 625,
    "anio_2019": 476,
    "anio_2020": 528,
    "anio_2021": 410,
    "anio_2022": 377,
    "anio_2023": 258,
    "anio_2024": 392,
    "anio_2025": 302,
    "variacion_porcentaje": -22.96,
    "total_bogota": 4294
  },
  {
    "codigo_localidad": "01",
    "nombre_localidad": "Usaquén",
    "lat": 4.7490,
    "lng": -74.0275,
    "mes": "Ene-Sep (2024vs2025)",
    "tipo": "Hurto a Comercio",
    "anio_2018": 986,
    "anio_2019": 1170,
    "anio_2020": 798,
    "anio_2021": 706,
    "anio_2022": 688,
    "anio_2023": 719,
    "anio_2024": 700,
    "anio_2025": 617,
    "variacion_porcentaje": -11.86,
    "total_bogota": 6694
  },
  {
    "codigo_localidad": "01",
    "nombre_localidad": "Usaquén",
    "lat": 4.7499,
    "lng": -74.0275,
    "mes": "Ene-Sep (2024vs2025)",
    "tipo": "Hurto de Celulares",
    "anio_2018": 4191,
    "anio_2019": 3400,
    "anio_2020": 2548,
    "anio_2021": 2863,
    "anio_2022": 2731,
    "anio_2023": 1983,
    "anio_2024": 0,
    "anio_2025": 1984,
    "variacion_porcentaje": 0,
    "total_bogota": 24392
  },
  {
    "codigo_localidad": "01",
    "nombre_localidad": "Usaquén",
    "lat": 4.7499,
    "lng": -74.0275,
    "mes": "Ene-Sep (2024vs2025)",
    "tipo": "Hurto de Motocicletas",
    "anio_2018": 58,
    "anio_2019": 87,
    "anio_2020": 87,
    "anio_2021": 97,
    "anio_2022": 57,
    "anio_2023": 67,
    "anio_2024": 109,
    "anio_2025": 85,
    "variacion_porcentaje": -22.02,
    "total_bogota": 3449
  },
  {
    "codigo_localidad": "01",
    "nombre_localidad": "Usaquén",
    "lat": 4.7499,
    "lng": -74.0275,
    "mes": "Ene-Sep (2024vs2025)",
    "tipo": "Delitos Sexuales",
    "anio_2018": 212,
    "anio_2019": 237,
    "anio_2020": 155,
    "anio_2021": 200,
    "anio_2022": 185,
    "anio_2023": 189,
    "anio_2024": 349,
    "anio_2025": 271,
    "variacion_porcentaje": -22.35,
    "total_bogota": 6968
  },
  {
    "codigo_localidad": "01",
    "nombre_localidad": "Usaquén",
    "lat": 4.7499,
    "lng": -74.0275,
    "mes": "Ene-Sep (2024vs2025)",
    "tipo": "Violencia Intrafamiliar",
    "anio_2018": 1125,
    "anio_2019": 1195,
    "anio_2020": 1228,
    "anio_2021": 1163,
    "anio_2022": 970,
    "anio_2023": 898,
    "anio_2024": 1700,
    "anio_2025": 1171,
    "variacion_porcentaje": -31.12,
    "total_bogota": 38257
  },
  {
    "codigo_localidad": "02",
    "nombre_localidad": "Chapinero",
    "lat": 4.6486,
    "lng": -74.0570,
    "mes": "Ene-Sep (2024vs2025)",
    "tipo": "Homicidios",
    "anio_2018": 7,
    "anio_2019": 11,
    "anio_2020": 4,
    "anio_2021": 6,
    "anio_2022": 11,
    "anio_2023": 11,
    "anio_2024": 14,
    "anio_2025": 11,
    "variacion_porcentaje": -21.43,
    "total_bogota": 875
  },
  {
    "codigo_localidad": "02",
    "nombre_localidad": "Chapinero",
    "lat": 4.6486,
    "lng": -74.0570,
    "mes": "Ene-Sep (2024vs2025)",
    "tipo": "Lesiones Personales",
    "anio_2018": 640,
    "anio_2019": 473,
    "anio_2020": 278,
    "anio_2021": 381,
    "anio_2022": 476,
    "anio_2023": 390,
    "anio_2024": 432,
    "anio_2025": 349,
    "variacion_porcentaje": -19.21,
    "total_bogota": 15137
  },
  {
    "codigo_localidad": "02",
    "nombre_localidad": "Chapinero",
    "lat": 4.6486,
    "lng": -74.0570,
    "mes": "Ene-Sep (2024vs2025)",
    "tipo": "Hurto a Personas",
    "anio_2018": 7296,
    "anio_2019": 9971,
    "anio_2020": 3965,
    "anio_2021": 5723,
    "anio_2022": 8270,
    "anio_2023": 11550,
    "anio_2024": 8285,
    "anio_2025": 6894,
    "variacion_porcentaje": -16.79,
    "total_bogota": 100894
  },
  {
    "codigo_localidad": "02",
    "nombre_localidad": "Chapinero",
    "lat": 4.6486,
    "lng": -74.0570,
    "mes": "Ene-Sep (2024vs2025)",
    "tipo": "Hurto a Residencias",
    "anio_2018": 327,
    "anio_2019": 316,
    "anio_2020": 256,
    "anio_2021": 247,
    "anio_2022": 221,
    "anio_2023": 256,
    "anio_2024": 212,
    "anio_2025": 221,
    "variacion_porcentaje": 4.25,
    "total_bogota": 4701
  },
  {
    "codigo_localidad": "02",
    "nombre_localidad": "Chapinero",
    "lat": 4.6486,
    "lng": -74.0570,
    "mes": "Ene-Sep (2024vs2025)",
    "tipo": "Hurto de Automotores",
    "anio_2018": 40,
    "anio_2019": 34,
    "anio_2020": 33,
    "anio_2021": 37,
    "anio_2022": 38,
    "anio_2023": 38,
    "anio_2024": 49,
    "anio_2025": 30,
    "variacion_porcentaje": -38.78,
    "total_bogota": 2401
  },
  {
    "codigo_localidad": "02",
    "nombre_localidad": "Chapinero",
    "lat": 4.6486,
    "lng": -74.0570,
    "mes": "Ene-Sep (2024vs2025)",
    "tipo": "Hurto de Bicicletas",
    "anio_2018": 394,
    "anio_2019": 331,
    "anio_2020": 292,
    "anio_2021": 224,
    "anio_2022": 247,
    "anio_2023": 183,
    "anio_2024": 193,
    "anio_2025": 203,
    "variacion_porcentaje": 5.18,
    "total_bogota": 4294
  },
  {
    "codigo_localidad": "02",
    "nombre_localidad": "Chapinero",
    "lat": 4.6486,
    "lng": -74.0570,
    "mes": "Ene-Sep (2024vs2025)",
    "tipo": "Hurto a Comercio",
    "anio_2018": 1224,
    "anio_2019": 1481,
    "anio_2020": 801,
    "anio_2021": 628,
    "anio_2022": 636,
    "anio_2023": 791,
    "anio_2024": 741,
    "anio_2025": 574,
    "variacion_porcentaje": -22.54,
    "total_bogota": 6694
  },
  {
    "codigo_localidad": "02",
    "nombre_localidad": "Chapinero",
    "lat": 4.6486,
    "lng": -74.0570,
    "mes": "Ene-Sep (2024vs2025)",
    "tipo": "Hurto de Celulares",
    "anio_2018": 5955,
    "anio_2019": 4772,
    "anio_2020": 2359,
    "anio_2021": 3342,
    "anio_2022": 4509,
    "anio_2023": 4373,
    "anio_2024": 0,
    "anio_2025": 2606,
    "variacion_porcentaje": 0,
    "total_bogota": 24392
  },
  {
    "codigo_localidad": "02",
    "nombre_localidad": "Chapinero",
    "lat": 4.6486,
    "lng": -74.0570,
    "mes": "Ene-Sep (2024vs2025)",
    "tipo": "Hurto de Motocicletas",
    "anio_2018": 23,
    "anio_2019": 26,
    "anio_2020": 18,
    "anio_2021": 32,
    "anio_2022": 51,
    "anio_2023": 63,
    "anio_2024": 54,
    "anio_2025": 46,
    "variacion_porcentaje": -14.81,
    "total_bogota": 3449
  },
  {
    "codigo_localidad": "02",
    "nombre_localidad": "Chapinero",
    "lat": 4.6486,
    "lng": -74.0570,
    "mes": "Ene-Sep (2024vs2025)",
    "tipo": "Delitos Sexuales",
    "anio_2018": 158,
    "anio_2019": 109,
    "anio_2020": 80,
    "anio_2021": 103,
    "anio_2022": 133,
    "anio_2023": 111,
    "anio_2024": 298,
    "anio_2025": 151,
    "variacion_porcentaje": -49.33,
    "total_bogota": 6968
  },
  {
    "codigo_localidad": "02",
    "nombre_localidad": "Chapinero",
    "lat": 4.6486,
    "lng": -74.0570,
    "mes": "Ene-Sep (2024vs2025)",
    "tipo": "Violencia Intrafamiliar",
    "anio_2018": 469,
    "anio_2019": 351,
    "anio_2020": 402,
    "anio_2021": 405,
    "anio_2022": 578,
    "anio_2023": 458,
    "anio_2024": 772,
    "anio_2025": 622,
    "variacion_porcentaje": -19.43,
    "total_bogota": 38257
  },
  {
    "codigo_localidad": "03",
    "nombre_localidad": "Santa Fe",
    "lat": 4.5981,
    "lng": -74.0760,
    "mes": "Ene-Sep (2024vs2025)",
    "tipo": "Homicidios",
    "anio_2018": 19,
    "anio_2019": 24,
    "anio_2020": 30,
    "anio_2021": 36,
    "anio_2022": 44,
    "anio_2023": 39,
    "anio_2024": 64,
    "anio_2025": 51,
    "variacion_porcentaje": -20.31,
    "total_bogota": 875
},
{
    "codigo_localidad": "03",
    "nombre_localidad": "Santa Fe",
    "lat": 4.5981,
    "lng": -74.0760,
    "mes": "Ene-Sep (2024vs2025)",
    "tipo": "Lesiones Personales",
    "anio_2018": 946,
    "anio_2019": 635,
    "anio_2020": 459,
    "anio_2021": 594,
    "anio_2022": 628,
    "anio_2023": 573,
    "anio_2024": 472,
    "anio_2025": 477,
    "variacion_porcentaje": 1.06,
    "total_bogota": 15137
},
{
    "codigo_localidad": "03",
    "nombre_localidad": "Santa Fe",
    "lat": 4.5981,
    "lng": -74.0760,
    "mes": "Ene-Sep (2024vs2025)",
    "tipo": "Hurto a Personas",
    "anio_2018": 5309,
    "anio_2019": 5770,
    "anio_2020": 2794,
    "anio_2021": 3381,
    "anio_2022": 5372,
    "anio_2023": 6393,
    "anio_2024": 5931,
    "anio_2025": 4731,
    "variacion_porcentaje": -20.23,
    "total_bogota": 100894
},
{
    "codigo_localidad": "03",
    "nombre_localidad": "Santa Fe",
    "lat": 4.5981,
    "lng": -74.0760,
    "mes": "Ene-Sep (2024vs2025)",
    "tipo": "Hurto a Residencias",
    "anio_2018": 144,
    "anio_2019": 108,
    "anio_2020": 99,
    "anio_2021": 86,
    "anio_2022": 92,
    "anio_2023": 127,
    "anio_2024": 104,
    "anio_2025": 103,
    "variacion_porcentaje": -0.96,
    "total_bogota": 4701
},
{
    "codigo_localidad": "03",
    "nombre_localidad": "Santa Fe",
    "lat": 4.5981,
    "lng": -74.0760,
    "mes": "Ene-Sep (2024vs2025)",
    "tipo": "Hurto de Automotores",
    "anio_2018": 28,
    "anio_2019": 24,
    "anio_2020": 29,
    "anio_2021": 25,
    "anio_2022": 29,
    "anio_2023": 29,
    "anio_2024": 39,
    "anio_2025": 34,
    "variacion_porcentaje": -12.82,
    "total_bogota": 2401
},
{
    "codigo_localidad": "03",
    "nombre_localidad": "Santa Fe",
    "lat": 4.5981,
    "lng": -74.0760,
    "mes": "Ene-Sep (2024vs2025)",
    "tipo": "Hurto de Bicicletas",
    "anio_2018": 163,
    "anio_2019": 116,
    "anio_2020": 159,
    "anio_2021": 217,
    "anio_2022": 156,
    "anio_2023": 139,
    "anio_2024": 105,
    "anio_2025": 103,
    "variacion_porcentaje": -1.90,
    "total_bogota": 4294
},
{
    "codigo_localidad": "03",
    "nombre_localidad": "Santa Fe",
    "lat": 4.5981,
    "lng": -74.0760,
    "mes": "Ene-Sep (2024vs2025)",
    "tipo": "Hurto a Comercio",
    "anio_2018": 732,
    "anio_2019": 634,
    "anio_2020": 334,
    "anio_2021": 451,
    "anio_2022": 385,
    "anio_2023": 530,
    "anio_2024": 417,
    "anio_2025": 217,
    "variacion_porcentaje": -47.96,
    "total_bogota": 6694
},
{
    "codigo_localidad": "03",
    "nombre_localidad": "Santa Fe",
    "lat": 4.5981,
    "lng": -74.0760,
    "mes": "Ene-Sep (2024vs2025)",
    "tipo": "Hurto de Celulares",
    "anio_2018": 3512,
    "anio_2019": 2910,
    "anio_2020": 1700,
    "anio_2021": 1831,
    "anio_2022": 2778,
    "anio_2023": 2237,
    "anio_2024": 0,
    "anio_2025": 1318,
    "variacion_porcentaje": 0,
    "total_bogota": 24392
},
{
    "codigo_localidad": "03",
    "nombre_localidad": "Santa Fe",
    "lat": 4.5981,
    "lng": -74.0760,
    "mes": "Ene-Sep (2024vs2025)",
    "tipo": "Hurto de Motocicletas",
    "anio_2018": 41,
    "anio_2019": 23,
    "anio_2020": 16,
    "anio_2021": 48,
    "anio_2022": 43,
    "anio_2023": 47,
    "anio_2024": 52,
    "anio_2025": 62,
    "variacion_porcentaje": 19.23,
    "total_bogota": 3449
},
{
    "codigo_localidad": "03",
    "nombre_localidad": "Santa Fe",
    "lat": 4.5981,
    "lng": -74.0760,
    "mes": "Ene-Sep (2024vs2025)",
    "tipo": "Delitos Sexuales",
    "anio_2018": 122,
    "anio_2019": 124,
    "anio_2020": 93,
    "anio_2021": 194,
    "anio_2022": 187,
    "anio_2023": 173,
    "anio_2024": 297,
    "anio_2025": 260,
    "variacion_porcentaje": -12.46,
    "total_bogota": 6968
},
{
    "codigo_localidad": "03",
    "nombre_localidad": "Santa Fe",
    "lat": 4.5981,
    "lng": -74.0760,
    "mes": "Ene-Sep (2024vs2025)",
    "tipo": "Violencia Intrafamiliar",
    "anio_2018": 524,
    "anio_2019": 417,
    "anio_2020": 535,
    "anio_2021": 733,
    "anio_2022": 749,
    "anio_2023": 708,
    "anio_2024": 908,
    "anio_2025": 947,
    "variacion_porcentaje": 4.30,
    "total_bogota": 38257
 },
  {
    "codigo_localidad": "01",
    "nombre_localidad": "Usaquén",
    "lat": 4.7499,
    "lng": -74.0275,
    "mes": "Ene-Sep (2024vs2025)",
    "tipo": "Homicidios",
    "anio_2018": 25,
    "anio_2019": 20,
    "anio_2020": 39,
    "anio_2021": 29,
    "anio_2022": 22,
    "anio_2023": 24,
    "anio_2024": 31,
    "anio_2025": 36,
    "variacion_porcentaje": 16.13,
    "total_bogota": 875
  },
  {
    "codigo_localidad": "01",
    "nombre_localidad": "Usaquén",
    "lat": 4.7499,
    "lng": -74.0275,
    "mes": "Ene-Sep (2024vs2025)",
    "tipo": "Lesiones Personales",
    "anio_2018": 1002,
    "anio_2019": 712,
    "anio_2020": 482,
    "anio_2021": 786,
    "anio_2022": 607,
    "anio_2023": 560,
    "anio_2024": 599,
    "anio_2025": 594,
    "variacion_porcentaje": -0.83,
    "total_bogota": 15137
  },
  {
    "codigo_localidad": "02",
    "nombre_localidad": "Chapinero",
    "lat": 4.6486,
    "lng": -74.0570,
    "mes": "Ene-Sep (2024vs2025)",
    "tipo": "Homicidios",
    "anio_2018": 7,
    "anio_2019": 11,
    "anio_2020": 4,
    "anio_2021": 6,
    "anio_2022": 11,
    "anio_2023": 11,
    "anio_2024": 14,
    "anio_2025": 11,
    "variacion_porcentaje": -21.43,
    "total_bogota": 875
  },
  {
    "codigo_localidad": "03",
    "nombre_localidad": "Santa Fe",
    "lat": 4.5981,
    "lng": -74.0760,
    "mes": "Ene-Sep (2024vs2025)",
    "tipo": "Homicidios",
    "anio_2018": 19,
    "anio_2019": 24,
    "anio_2020": 30,
    "anio_2021": 36,
    "anio_2022": 44,
    "anio_2023": 39,
    "anio_2024": 64,
    "anio_2025": 51,
    "variacion_porcentaje": -20.31,
    "total_bogota": 875
  },
  {
    "codigo_localidad": "03",
    "nombre_localidad": "Santa Fe",
    "lat": 4.5981,
    "lng": -74.0760,
    "mes": "Ene-Sep (2024vs2025)",
    "tipo": "Lesiones Personales",
    "anio_2018": 946,
    "anio_2019": 635,
    "anio_2020": 459,
    "anio_2021": 594,
    "anio_2022": 628,
    "anio_2023": 573,
    "anio_2024": 472,
    "anio_2025": 477,
    "variacion_porcentaje": 1.06,
    "total_bogota": 15137
  },
  {
    "codigo_localidad": "04",
    "nombre_localidad": "San Cristóbal",
    "lat": 4.5700,
    "lng": -74.1060,
    "mes": "Ene-Sep (2024vs2025)",
    "tipo": "Homicidios",
    "anio_2018": 37,
    "anio_2019": 27,
    "anio_2020": 41,
    "anio_2021": 49,
    "anio_2022": 37,
    "anio_2023": 43,
    "anio_2024": 42,
    "anio_2025": 62,
    "variacion_porcentaje": 47.62,
    "total_bogota": 875
  },
  {
    "codigo_localidad": "04",
    "nombre_localidad": "San Cristóbal",
    "lat": 4.5700,
    "lng": -74.1060,
    "mes": "Ene-Sep (2024vs2025)",
    "tipo": "Lesiones Personales",
    "anio_2018": 1326,
    "anio_2019": 1149,
    "anio_2020": 796,
    "anio_2021": 1013,
    "anio_2022": 849,
    "anio_2023": 844,
    "anio_2024": 800,
    "anio_2025": 786,
    "variacion_porcentaje": -1.75,
    "total_bogota": 15137
},
{
    "codigo_localidad": "05",
    "nombre_localidad": "Usme",
    "lat": 4.5350,
    "lng": -74.1700,
    "mes": "Ene-Sep (2024vs2025)",
    "tipo": "Homicidios",
    "anio_2018": 61,
    "anio_2019": 68,
    "anio_2020": 44,
    "anio_2021": 53,
    "anio_2022": 52,
    "anio_2023": 45,
    "anio_2024": 70,
    "anio_2025": 54,
    "variacion_porcentaje": -22.86,
    "total_bogota": 875
},
{
    "codigo_localidad": "05",
    "nombre_localidad": "Usme",
    "lat": 4.5350,
    "lng": -74.1700,
    "mes": "Ene-Sep (2024vs2025)",
    "tipo": "Lesiones Personales",
    "anio_2018": 1199,
    "anio_2019": 1182,
    "anio_2020": 833,
    "anio_2021": 1072,
    "anio_2022": 875,
    "anio_2023": 736,
    "anio_2024": 745,
    "anio_2025": 749,
    "variacion_porcentaje": 0.54,
    "total_bogota": 15137
},
{
    "codigo_localidad": "05",
    "nombre_localidad": "Usme",
    "lat": 4.5350,
    "lng": -74.1700,
    "mes": "Ene-Sep (2024vs2025)",
    "tipo": "Hurto a Personas",
    "anio_2018": 1338,
    "anio_2019": 1666,
    "anio_2020": 1363,
    "anio_2021": 1697,
    "anio_2022": 1952,
    "anio_2023": 2442,
    "anio_2024": 1757,
    "anio_2025": 1707,
    "variacion_porcentaje": -2.85,
    "total_bogota": 100894
},
{
    "codigo_localidad": "05",
    "nombre_localidad": "Usme",
    "lat": 4.5350,
    "lng": -74.1700,
    "mes": "Ene-Sep (2024vs2025)",
    "tipo": "Hurto a Residencias",
    "anio_2018": 317,
    "anio_2019": 346,
    "anio_2020": 233,
    "anio_2021": 208,
    "anio_2022": 192,
    "anio_2023": 279,
    "anio_2024": 188,
    "anio_2025": 105,
    "variacion_porcentaje": -44.15,
    "total_bogota": 4701
},
{
    "codigo_localidad": "05",
    "nombre_localidad": "Usme",
    "lat": 4.5350,
    "lng": -74.1700,
    "mes": "Ene-Sep (2024vs2025)",
    "tipo": "Hurto de Automotores",
    "anio_2018": 55,
    "anio_2019": 82,
    "anio_2020": 59,
    "anio_2021": 63,
    "anio_2022": 75,
    "anio_2023": 116,
    "anio_2024": 113,
    "anio_2025": 80,
    "variacion_porcentaje": -29.2,
    "total_bogota": 2401
},
{
    "codigo_localidad": "05",
    "nombre_localidad": "Usme",
    "lat": 4.5350,
    "lng": -74.1700,
    "mes": "Ene-Sep (2024vs2025)",
    "tipo": "Hurto de Bicicletas",
    "anio_2018": 27,
    "anio_2019": 27,
    "anio_2020": 67,
    "anio_2021": 65,
    "anio_2022": 41,
    "anio_2023": 35,
    "anio_2024": 36,
    "anio_2025": 30,
    "variacion_porcentaje": -16.67,
    "total_bogota": 4294
},
{
    "codigo_localidad": "05",
    "nombre_localidad": "Usme",
    "lat": 4.5350,
    "lng": -74.1700,
    "mes": "Ene-Sep (2024vs2025)",
    "tipo": "Hurto a Comercio",
    "anio_2018": 308,
    "anio_2019": 417,
    "anio_2020": 236,
    "anio_2021": 209,
    "anio_2022": 175,
    "anio_2023": 245,
    "anio_2024": 203,
    "anio_2025": 152,
    "variacion_porcentaje": -25.12,
    "total_bogota": 6694
},
{
    "codigo_localidad": "05",
    "nombre_localidad": "Usme",
    "lat": 4.5350,
    "lng": -74.1700,
    "mes": "Ene-Sep (2024vs2025)",
    "tipo": "Hurto de Celulares",
    "anio_2018": 861,
    "anio_2019": 819,
    "anio_2020": 851,
    "anio_2021": 990,
    "anio_2022": 913,
    "anio_2023": 760,
    "anio_2024": 0,
    "anio_2025": 437,
    "variacion_porcentaje": 0,
    "total_bogota": 24392
},
{
    "codigo_localidad": "05",
    "nombre_localidad": "Usme",
    "lat": 4.5350,
    "lng": -74.1700,
    "mes": "Ene-Sep (2024vs2025)",
    "tipo": "Hurto de Motocicletas",
    "anio_2018": 144,
    "anio_2019": 119,
    "anio_2020": 96,
    "anio_2021": 152,
    "anio_2022": 158,
    "anio_2023": 185,
    "anio_2024": 167,
    "anio_2025": 165,
    "variacion_porcentaje": -1.2,
    "total_bogota": 3449
},
{
    "codigo_localidad": "05",
    "nombre_localidad": "Usme",
    "lat": 4.5350,
    "lng": -74.1700,
    "mes": "Ene-Sep (2024vs2025)",
    "tipo": "Delitos Sexuales",
    "anio_2018": 268,
    "anio_2019": 355,
    "anio_2020": 264,
    "anio_2021": 295,
    "anio_2022": 314,
    "anio_2023": 316,
    "anio_2024": 524,
    "anio_2025": 330,
    "variacion_porcentaje": -37.02,
    "total_bogota": 6968
},
{
    "codigo_localidad": "05",
    "nombre_localidad": "Usme",
    "lat": 4.5350,
    "lng": -74.1700,
    "mes": "Ene-Sep (2024vs2025)",
    "tipo": "Violencia Intrafamiliar",
    "anio_2018": 1485,
    "anio_2019": 1608,
    "anio_2020": 1738,
    "anio_2021": 1617,
    "anio_2022": 1499,
    "anio_2023": 1301,
    "anio_2024": 1386,
    "anio_2025": 1130,
    "variacion_porcentaje": -18.47,
    "total_bogota": 38257
},
{
    "codigo_localidad": "06",
    "nombre_localidad": "Tunjuelito",
    "lat": 4.5920,
    "lng": -74.1620,
    "mes": "Ene-Sep (2024vs2025)",
    "tipo": "Homicidios",
    "anio_2018": 19,
    "anio_2019": 33,
    "anio_2020": 13,
    "anio_2021": 21,
    "anio_2022": 17,
    "anio_2023": 15,
    "anio_2024": 20,
    "anio_2025": 16,
    "variacion_porcentaje": -20,
    "total_bogota": 875
},
{
    "codigo_localidad": "06",
    "nombre_localidad": "Tunjuelito",
    "lat": 4.5920,
    "lng": -74.1620,
    "mes": "Ene-Sep (2024vs2025)",
    "tipo": "Lesiones Personales",
    "anio_2018": 680,
    "anio_2019": 696,
    "anio_2020": 378,
    "anio_2021": 448,
    "anio_2022": 356,
    "anio_2023": 347,
    "anio_2024": 410,
    "anio_2025": 333,
    "variacion_porcentaje": -18.78,
    "total_bogota": 15137
},
{
    "codigo_localidad": "06",
    "nombre_localidad": "Tunjuelito",
    "lat": 4.5920,
    "lng": -74.1620,
    "mes": "Ene-Sep (2024vs2025)",
    "tipo": "Hurto a Personas",
    "anio_2018": 1605,
    "anio_2019": 1880,
    "anio_2020": 1410,
    "anio_2021": 1765,
    "anio_2022": 1886,
    "anio_2023": 1969,
    "anio_2024": 1716,
    "anio_2025": 1919,
    "variacion_porcentaje": 11.83,
    "total_bogota": 100894
},
{
    "codigo_localidad": "06",
    "nombre_localidad": "Tunjuelito",
    "lat": 4.5920,
    "lng": -74.1620,
    "mes": "Ene-Sep (2024vs2025)",
    "tipo": "Hurto a Residencias",
    "anio_2018": 162,
    "anio_2019": 123,
    "anio_2020": 116,
    "anio_2021": 111,
    "anio_2022": 75,
    "anio_2023": 77,
    "anio_2024": 75,
    "anio_2025": 73,
    "variacion_porcentaje": -2.67,
    "total_bogota": 4701
},
{
    "codigo_localidad": "06",
    "nombre_localidad": "Tunjuelito",
    "lat": 4.5920,
    "lng": -74.1620,
    "mes": "Ene-Sep (2024vs2025)",
    "tipo": "Hurto de Automotores",
    "anio_2018": 80,
    "anio_2019": 51,
    "anio_2020": 56,
    "anio_2021": 46,
    "anio_2022": 63,
    "anio_2023": 55,
    "anio_2024": 61,
    "anio_2025": 68,
    "variacion_porcentaje": 11.48,
    "total_bogota": 2401
},
{
    "codigo_localidad": "06",
    "nombre_localidad": "Tunjuelito",
    "lat": 4.5920,
    "lng": -74.1620,
    "mes": "Ene-Sep (2024vs2025)",
    "tipo": "Hurto de Bicicletas",
    "anio_2018": 101,
    "anio_2019": 102,
    "anio_2020": 181,
    "anio_2021": 177,
    "anio_2022": 112,
    "anio_2023": 99,
    "anio_2024": 99,
    "anio_2025": 82,
    "variacion_porcentaje": -17.17,
    "total_bogota": 4294
},
{
    "codigo_localidad": "06",
    "nombre_localidad": "Tunjuelito",
    "lat": 4.5920,
    "lng": -74.1620,
    "mes": "Ene-Sep (2024vs2025)",
    "tipo": "Hurto a Comercio",
    "anio_2018": 280,
    "anio_2019": 262,
    "anio_2020": 223,
    "anio_2021": 157,
    "anio_2022": 129,
    "anio_2023": 126,
    "anio_2024": 125,
    "anio_2025": 125,
    "variacion_porcentaje": 0,
    "total_bogota": 6694
},
{
    "codigo_localidad": "06",
    "nombre_localidad": "Tunjuelito",
    "lat": 4.5920,
    "lng": -74.1620,
    "mes": "Ene-Sep (2024vs2025)",
    "tipo": "Hurto de Celulares",
    "anio_2018": 1039,
    "anio_2019": 925,
    "anio_2020": 837,
    "anio_2021": 927,
    "anio_2022": 889,
    "anio_2023": 603,
    "anio_2024": 0,
    "anio_2025": 479,
    "variacion_porcentaje": 0,
    "total_bogota": 24392
},
{
    "codigo_localidad": "06",
    "nombre_localidad": "Tunjuelito",
    "lat": 4.5920,
    "lng": -74.1620,
    "mes": "Ene-Sep (2024vs2025)",
    "tipo": "Hurto de Motocicletas",
    "anio_2018": 93,
    "anio_2019": 64,
    "anio_2020": 72,
    "anio_2021": 85,
    "anio_2022": 77,
    "anio_2023": 66,
    "anio_2024": 65,
    "anio_2025": 77,
    "variacion_porcentaje": 18.46,
    "total_bogota": 3449
},
{
    "codigo_localidad": "06",
    "nombre_localidad": "Tunjuelito",
    "lat": 4.5920,
    "lng": -74.1620,
    "mes": "Ene-Sep (2024vs2025)",
    "tipo": "Delitos Sexuales",
    "anio_2018": 116,
    "anio_2019": 123,
    "anio_2020": 87,
    "anio_2021": 106,
    "anio_2022": 137,
    "anio_2023": 110,
    "anio_2024": 172,
    "anio_2025": 142,
    "variacion_porcentaje": -17.44,
    "total_bogota": 6968
},
{
    "codigo_localidad": "06",
    "nombre_localidad": "Tunjuelito",
    "lat": 4.5920,
    "lng": -74.1620,
    "mes": "Ene-Sep (2024vs2025)",
    "tipo": "Violencia Intrafamiliar",
    "anio_2018": 727,
    "anio_2019": 817,
    "anio_2020": 705,
    "anio_2021": 641,
    "anio_2022": 684,
    "anio_2023": 531,
    "anio_2024": 536,
    "anio_2025": 775,
    "variacion_porcentaje": 44.59,
    "total_bogota": 38257
},
{
    "codigo_localidad": "07",
    "nombre_localidad": "Bosa",
    "lat": 4.5980,
    "lng": -74.1990,
    "mes": "Ene-Sep (2024vs2025)",
    "tipo": "Homicidios",
    "anio_2018": 76,
    "anio_2019": 73,
    "anio_2020": 59,
    "anio_2021": 87,
    "anio_2022": 65,
    "anio_2023": 86,
    "anio_2024": 91,
    "anio_2025": 66,
    "variacion_porcentaje": -27.47,
    "total_bogota": 875
},
{
    "codigo_localidad": "07",
    "nombre_localidad": "Bosa",
    "lat": 4.5980,
    "lng": -74.1990,
    "mes": "Ene-Sep (2024vs2025)",
    "tipo": "Lesiones Personales",
    "anio_2018": 1720,
    "anio_2019": 1579,
    "anio_2020": 1031,
    "anio_2021": 1627,
    "anio_2022": 1264,
    "anio_2023": 1182,
    "anio_2024": 1012,
    "anio_2025": 967,
    "variacion_porcentaje": -4.45,
    "total_bogota": 15137
},
{
    "codigo_localidad": "07",
    "nombre_localidad": "Bosa",
    "lat": 4.5980,
    "lng": -74.1990,
    "mes": "Ene-Sep (2024vs2025)",
    "tipo": "Hurto a Personas",
    "anio_2018": 3140,
    "anio_2019": 3864,
    "anio_2020": 3207,
    "anio_2021": 4523,
    "anio_2022": 4727,
    "anio_2023": 5609,
    "anio_2024": 3940,
    "anio_2025": 4165,
    "variacion_porcentaje": 5.71,
    "total_bogota": 100894
},
{
    "codigo_localidad": "07",
    "nombre_localidad": "Bosa",
    "lat": 4.5980,
    "lng": -74.1990,
    "mes": "Ene-Sep (2024vs2025)",
    "tipo": "Hurto a Residencias",
    "anio_2018": 606,
    "anio_2019": 629,
    "anio_2020": 473,
    "anio_2021": 385,
    "anio_2022": 298,
    "anio_2023": 278,
    "anio_2024": 257,
    "anio_2025": 191,
    "variacion_porcentaje": -25.68,
    "total_bogota": 4701
},
{
    "codigo_localidad": "07",
    "nombre_localidad": "Bosa",
    "lat": 4.5980,
    "lng": -74.1990,
    "mes": "Ene-Sep (2024vs2025)",
    "tipo": "Hurto de Automotores",
    "anio_2018": 146,
    "anio_2019": 149,
    "anio_2020": 158,
    "anio_2021": 185,
    "anio_2022": 191,
    "anio_2023": 164,
    "anio_2024": 148,
    "anio_2025": 128,
    "variacion_porcentaje": -13.51,
    "total_bogota": 2401
},
{
    "codigo_localidad": "07",
    "nombre_localidad": "Bosa",
    "lat": 4.5980,
    "lng": -74.1990,
    "mes": "Ene-Sep (2024vs2025)",
    "tipo": "Hurto de Bicicletas",
    "anio_2018": 317,
    "anio_2019": 452,
    "anio_2020": 759,
    "anio_2021": 735,
    "anio_2022": 500,
    "anio_2023": 425,
    "anio_2024": 395,
    "anio_2025": 364,
    "variacion_porcentaje": -7.85,
    "total_bogota": 4294
},
{
    "codigo_localidad": "07",
    "nombre_localidad": "Bosa",
    "lat": 4.5980,
    "lng": -74.1990,
    "mes": "Ene-Sep (2024vs2025)",
    "tipo": "Hurto a Comercio",
    "anio_2018": 561,
    "anio_2019": 487,
    "anio_2020": 318,
    "anio_2021": 364,
    "anio_2022": 327,
    "anio_2023": 401,
    "anio_2024": 279,
    "anio_2025": 181,
    "variacion_porcentaje": -35.13,
    "total_bogota": 6694
},
{
    "codigo_localidad": "07",
    "nombre_localidad": "Bosa",
    "lat": 4.5980,
    "lng": -74.1990,
    "mes": "Ene-Sep (2024vs2025)",
    "tipo": "Hurto de Celulares",
    "anio_2018": 2091,
    "anio_2019": 1930,
    "anio_2020": 1637,
    "anio_2021": 2316,
    "anio_2022": 2127,
    "anio_2023": 1862,
    "anio_2024": 0,
    "anio_2025": 1029,
    "variacion_porcentaje": 0,
    "total_bogota": 24392
},
{
    "codigo_localidad": "07",
    "nombre_localidad": "Bosa",
    "lat": 4.5980,
    "lng": -74.1990,
    "mes": "Ene-Sep (2024vs2025)",
    "tipo": "Hurto de Motocicletas",
    "anio_2018": 405,
    "anio_2019": 365,
    "anio_2020": 331,
    "anio_2021": 436,
    "anio_2022": 365,
    "anio_2023": 337,
    "anio_2024": 380,
    "anio_2025": 354,
    "variacion_porcentaje": -6.84,
    "total_bogota": 3449
},
{
    "codigo_localidad": "07",
    "nombre_localidad": "Bosa",
    "lat": 4.5980,
    "lng": -74.1990,
    "mes": "Ene-Sep (2024vs2025)",
    "tipo": "Delitos Sexuales",
    "anio_2018": 439,
    "anio_2019": 463,
    "anio_2020": 361,
    "anio_2021": 445,
    "anio_2022": 506,
    "anio_2023": 433,
    "anio_2024": 477,
    "anio_2025": 378,
    "variacion_porcentaje": -20.75,
    "total_bogota": 6968
},
{
    "codigo_localidad": "07",
    "nombre_localidad": "Bosa",
    "lat": 4.5980,
    "lng": -74.1990,
    "mes": "Ene-Sep (2024vs2025)",
    "tipo": "Violencia Intrafamiliar",
    "anio_2018": 3710,
    "anio_2019": 3462,
    "anio_2020": 3571,
    "anio_2021": 3019,
    "anio_2022": 2750,
    "anio_2023": 2595,
    "anio_2024": 2646,
    "anio_2025": 2276,
    "variacion_porcentaje": -13.98,
    "total_bogota": 38257
},
{
    "codigo_localidad": "08",
    "nombre_localidad": "Kennedy",
    "lat": 4.6350,
    "lng": -74.1630,
    "mes": "Ene-Sep (2024vs2025)",
    "tipo": "Homicidios",
    "anio_2018": 110,
    "anio_2019": 96,
    "anio_2020": 98,
    "anio_2021": 137,
    "anio_2022": 90,
    "anio_2023": 122,
    "anio_2024": 132,
    "anio_2025": 119,
    "variacion_porcentaje": -9.85,
    "total_bogota": 875
},
{
    "codigo_localidad": "08",
    "nombre_localidad": "Kennedy",
    "lat": 4.6350,
    "lng": -74.1630,
    "mes": "Ene-Sep (2024vs2025)",
    "tipo": "Lesiones Personales",
    "anio_2018": 2666,
    "anio_2019": 2423,
    "anio_2020": 1448,
    "anio_2021": 2252,
    "anio_2022": 1948,
    "anio_2023": 1664,
    "anio_2024": 1870,
    "anio_2025": 1434,
    "variacion_porcentaje": -23.32,
    "total_bogota": 15137
},
{
    "codigo_localidad": "08",
    "nombre_localidad": "Kennedy",
    "lat": 4.6350,
    "lng": -74.1630,
    "mes": "Ene-Sep (2024vs2025)",
    "tipo": "Hurto a Personas",
    "anio_2018": 8063,
    "anio_2019": 9588,
    "anio_2020": 6789,
    "anio_2021": 8664,
    "anio_2022": 10013,
    "anio_2023": 12766,
    "anio_2024": 8876,
    "anio_2025": 8178,
    "variacion_porcentaje": -7.86,
    "total_bogota": 100894
},
{
    "codigo_localidad": "08",
    "nombre_localidad": "Kennedy",
    "lat": 4.6350,
    "lng": -74.1630,
    "mes": "Ene-Sep (2024vs2025)",
    "tipo": "Hurto a Residencias",
    "anio_2018": 969,
    "anio_2019": 942,
    "anio_2020": 710,
    "anio_2021": 762,
    "anio_2022": 562,
    "anio_2023": 692,
    "anio_2024": 508,
    "anio_2025": 390,
    "variacion_porcentaje": -23.23,
    "total_bogota": 4701
},
{
    "codigo_localidad": "08",
    "nombre_localidad": "Kennedy",
    "lat": 4.6350,
    "lng": -74.1630,
    "mes": "Ene-Sep (2024vs2025)",
    "tipo": "Hurto de Automotores",
    "anio_2018": 604,
    "anio_2019": 599,
    "anio_2020": 479,
    "anio_2021": 595,
    "anio_2022": 612,
    "anio_2023": 741,
    "anio_2024": 810,
    "anio_2025": 462,
    "variacion_porcentaje": -42.96,
    "total_bogota": 2401
},
{
    "codigo_localidad": "08",
    "nombre_localidad": "Kennedy",
    "lat": 4.6350,
    "lng": -74.1630,
    "mes": "Ene-Sep (2024vs2025)",
    "tipo": "Hurto de Bicicletas",
    "anio_2018": 761,
    "anio_2019": 837,
    "anio_2020": 1368,
    "anio_2021": 1130,
    "anio_2022": 1071,
    "anio_2023": 1050,
    "anio_2024": 866,
    "anio_2025": 532,
    "variacion_porcentaje": -38.57,
    "total_bogota": 4294
},
{
    "codigo_localidad": "08",
    "nombre_localidad": "Kennedy",
    "lat": 4.6350,
    "lng": -74.1630,
    "mes": "Ene-Sep (2024vs2025)",
    "tipo": "Hurto a Comercio",
    "anio_2018": 1553,
    "anio_2019": 1356,
    "anio_2020": 815,
    "anio_2021": 847,
    "anio_2022": 675,
    "anio_2023": 784,
    "anio_2024": 676,
    "anio_2025": 517,
    "variacion_porcentaje": -23.52,
    "total_bogota": 6694
},
{
    "codigo_localidad": "08",
    "nombre_localidad": "Kennedy",
    "lat": 4.6350,
    "lng": -74.1630,
    "mes": "Ene-Sep (2024vs2025)",
    "tipo": "Hurto de Celulares",
    "anio_2018": 5398,
    "anio_2019": 4658,
    "anio_2020": 3579,
    "anio_2021": 4492,
    "anio_2022": 4661,
    "anio_2023": 4202,
    "anio_2024": 0,
    "anio_2025": 1779,
    "variacion_porcentaje": 0,
    "total_bogota": 24392
},
{
    "codigo_localidad": "08",
    "nombre_localidad": "Kennedy",
    "lat": 4.6350,
    "lng": -74.1630,
    "mes": "Ene-Sep (2024vs2025)",
    "tipo": "Hurto de Motocicletas",
    "anio_2018": 632,
    "anio_2019": 634,
    "anio_2020": 463,
    "anio_2021": 615,
    "anio_2022": 755,
    "anio_2023": 789,
    "anio_2024": 831,
    "anio_2025": 551,
    "variacion_porcentaje": -33.69,
    "total_bogota": 3449
},
{
    "codigo_localidad": "08",
    "nombre_localidad": "Kennedy",
    "lat": 4.6350,
    "lng": -74.1630,
    "mes": "Ene-Sep (2024vs2025)",
    "tipo": "Delitos Sexuales",
    "anio_2018": 496,
    "anio_2019": 560,
    "anio_2020": 424,
    "anio_2021": 462,
    "anio_2022": 542,
    "anio_2023": 451,
    "anio_2024": 647,
    "anio_2025": 445,
    "variacion_porcentaje": -31.22,
    "total_bogota": 6968
},
{
    "codigo_localidad": "08",
    "nombre_localidad": "Kennedy",
    "lat": 4.6350,
    "lng": -74.1630,
    "mes": "Ene-Sep (2024vs2025)",
    "tipo": "Violencia Intrafamiliar",
    "anio_2018": 3459,
    "anio_2019": 3742,
    "anio_2020": 3635,
    "anio_2021": 3177,
    "anio_2022": 3173,
    "anio_2023": 2503,
    "anio_2024": 3402,
    "anio_2025": 3321,
    "variacion_porcentaje": -2.38,
    "total_bogota": 38257
},
{
    "codigo_localidad": "09",
    "nombre_localidad": "Fontibón",
    "lat": 4.7100,
    "lng": -74.1500,
    "mes": "Ene-Sep (2024vs2025)",
    "tipo": "Homicidios",
    "anio_2018": 11,
    "anio_2019": 20,
    "anio_2020": 17,
    "anio_2021": 21,
    "anio_2022": 17,
    "anio_2023": 22,
    "anio_2024": 29,
    "anio_2025": 30,
    "variacion_porcentaje": 3.45,
    "total_bogota": 875
},
{
    "codigo_localidad": "09",
    "nombre_localidad": "Fontibón",
    "lat": 4.7100,
    "lng": -74.1500,
    "mes": "Ene-Sep (2024vs2025)",
    "tipo": "Lesiones Personales",
    "anio_2018": 838,
    "anio_2019": 635,
    "anio_2020": 393,
    "anio_2021": 638,
    "anio_2022": 676,
    "anio_2023": 564,
    "anio_2024": 469,
    "anio_2025": 348,
    "variacion_porcentaje": -25.80,
    "total_bogota": 15137
},
{
    "codigo_localidad": "09",
    "nombre_localidad": "Fontibón",
    "lat": 4.7100,
    "lng": -74.1500,
    "mes": "Ene-Sep (2024vs2025)",
    "tipo": "Hurto a Personas",
    "anio_2018": 4456,
    "anio_2019": 5682,
    "anio_2020": 3731,
    "anio_2021": 4833,
    "anio_2022": 6165,
    "anio_2023": 6775,
    "anio_2024": 6153,
    "anio_2025": 5621,
    "variacion_porcentaje": -8.65,
    "total_bogota": 100894
},
{
    "codigo_localidad": "09",
    "nombre_localidad": "Fontibón",
    "lat": 4.7100,
    "lng": -74.1500,
    "mes": "Ene-Sep (2024vs2025)",
    "tipo": "Hurto a Residencias",
    "anio_2018": 310,
    "anio_2019": 330,
    "anio_2020": 310,
    "anio_2021": 291,
    "anio_2022": 290,
    "anio_2023": 279,
    "anio_2024": 249,
    "anio_2025": 226,
    "variacion_porcentaje": -9.24,
    "total_bogota": 4701
},
{
    "codigo_localidad": "09",
    "nombre_localidad": "Fontibón",
    "lat": 4.7100,
    "lng": -74.1500,
    "mes": "Ene-Sep (2024vs2025)",
    "tipo": "Hurto de Automotores",
    "anio_2018": 108,
    "anio_2019": 112,
    "anio_2020": 106,
    "anio_2021": 107,
    "anio_2022": 119,
    "anio_2023": 106,
    "anio_2024": 93,
    "anio_2025": 80,
    "variacion_porcentaje": -13.98,
    "total_bogota": 2401
},
{
    "codigo_localidad": "09",
    "nombre_localidad": "Fontibón",
    "lat": 4.7100,
    "lng": -74.1500,
    "mes": "Ene-Sep (2024vs2025)",
    "tipo": "Hurto de Bicicletas",
    "anio_2018": 347,
    "anio_2019": 491,
    "anio_2020": 552,
    "anio_2021": 498,
    "anio_2022": 632,
    "anio_2023": 453,
    "anio_2024": 476,
    "anio_2025": 347,
    "variacion_porcentaje": -27.10,
    "total_bogota": 4294
},
{
    "codigo_localidad": "09",
    "nombre_localidad": "Fontibón",
    "lat": 4.7100,
    "lng": -74.1500,
    "mes": "Ene-Sep (2024vs2025)",
    "tipo": "Hurto a Comercio",
    "anio_2018": 1033,
    "anio_2019": 920,
    "anio_2020": 625,
    "anio_2021": 563,
    "anio_2022": 741,
    "anio_2023": 731,
    "anio_2024": 537,
    "anio_2025": 402,
    "variacion_porcentaje": -25.14,
    "total_bogota": 6694
},
{
    "codigo_localidad": "09",
    "nombre_localidad": "Fontibón",
    "lat": 4.7100,
    "lng": -74.1500,
    "mes": "Ene-Sep (2024vs2025)",
    "tipo": "Hurto de Celulares",
    "anio_2018": 2755,
    "anio_2019": 2756,
    "anio_2020": 2132,
    "anio_2021": 2599,
    "anio_2022": 2920,
    "anio_2023": 2346,
    "anio_2024": 0,
    "anio_2025": 1355,
    "variacion_porcentaje": 0,
    "total_bogota": 24392
},
{
    "codigo_localidad": "09",
    "nombre_localidad": "Fontibón",
    "lat": 4.7100,
    "lng": -74.1500,
    "mes": "Ene-Sep (2024vs2025)",
    "tipo": "Hurto de Motocicletas",
    "anio_2018": 140,
    "anio_2019": 100,
    "anio_2020": 109,
    "anio_2021": 104,
    "anio_2022": 128,
    "anio_2023": 142,
    "anio_2024": 115,
    "anio_2025": 125,
    "variacion_porcentaje": 8.70,
    "total_bogota": 3449
},
{
    "codigo_localidad": "09",
    "nombre_localidad": "Fontibón",
    "lat": 4.7100,
    "lng": -74.1500,
    "mes": "Ene-Sep (2024vs2025)",
    "tipo": "Delitos Sexuales",
    "anio_2018": 169,
    "anio_2019": 164,
    "anio_2020": 128,
    "anio_2021": 139,
    "anio_2022": 155,
    "anio_2023": 132,
    "anio_2024": 247,
    "anio_2025": 196,
    "variacion_porcentaje": -20.65,
    "total_bogota": 6968
},
{
    "codigo_localidad": "09",
    "nombre_localidad": "Fontibón",
    "lat": 4.7100,
    "lng": -74.1500,
    "mes": "Ene-Sep (2024vs2025)",
    "tipo": "Violencia Intrafamiliar",
    "anio_2018": 1018,
    "anio_2019": 1127,
    "anio_2020": 977,
    "anio_2021": 795,
    "anio_2022": 1106,
    "anio_2023": 879,
    "anio_2024": 1748,
    "anio_2025": 1684,
    "variacion_porcentaje": -3.66,
    "total_bogota": 38257
},
{
    "codigo_localidad": "10",
    "nombre_localidad": "Engativá",
    "lat": 4.7000,
    "lng": -74.1000,
    "mes": "Ene-Sep (2024vs2025)",
    "tipo": "Homicidios",
    "anio_2018": 30,
    "anio_2019": 41,
    "anio_2020": 36,
    "anio_2021": 33,
    "anio_2022": 33,
    "anio_2023": 45,
    "anio_2024": 47,
    "anio_2025": 34,
    "variacion_porcentaje": -27.66,
    "total_bogota": 875
},
{
    "codigo_localidad": "10",
    "nombre_localidad": "Engativá",
    "lat": 4.7000,
    "lng": -74.1000,
    "mes": "Ene-Sep (2024vs2025)",
    "tipo": "Lesiones Personales",
    "anio_2018": 1718,
    "anio_2019": 1219,
    "anio_2020": 868,
    "anio_2021": 1279,
    "anio_2022": 1264,
    "anio_2023": 1179,
    "anio_2024": 937,
    "anio_2025": 1020,
    "variacion_porcentaje": 8.86,
    "total_bogota": 15137
},
{
    "codigo_localidad": "10",
    "nombre_localidad": "Engativá",
    "lat": 4.7000,
    "lng": -74.1000,
    "mes": "Ene-Sep (2024vs2025)",
    "tipo": "Hurto a Personas",
    "anio_2018": 7106,
    "anio_2019": 8309,
    "anio_2020": 6473,
    "anio_2021": 8340,
    "anio_2022": 9399,
    "anio_2023": 12070,
    "anio_2024": 9116,
    "anio_2025": 8945,
    "variacion_porcentaje": -1.88,
    "total_bogota": 100894
},
{
    "codigo_localidad": "10",
    "nombre_localidad": "Engativá",
    "lat": 4.7000,
    "lng": -74.1000,
    "mes": "Ene-Sep (2024vs2025)",
    "tipo": "Hurto a Residencias",
    "anio_2018": 923,
    "anio_2019": 909,
    "anio_2020": 699,
    "anio_2021": 675,
    "anio_2022": 603,
    "anio_2023": 1003,
    "anio_2024": 507,
    "anio_2025": 510,
    "variacion_porcentaje": 0.59,
    "total_bogota": 4701
},
{
    "codigo_localidad": "10",
    "nombre_localidad": "Engativá",
    "lat": 4.7000,
    "lng": -74.1000,
    "mes": "Ene-Sep (2024vs2025)",
    "tipo": "Hurto de Automotores",
    "anio_2018": 347,
    "anio_2019": 379,
    "anio_2020": 286,
    "anio_2021": 413,
    "anio_2022": 343,
    "anio_2023": 350,
    "anio_2024": 314,
    "anio_2025": 273,
    "variacion_porcentaje": -13.06,
    "total_bogota": 2401
},
{
    "codigo_localidad": "10",
    "nombre_localidad": "Engativá",
    "lat": 4.7000,
    "lng": -74.1000,
    "mes": "Ene-Sep (2024vs2025)",
    "tipo": "Hurto de Bicicletas",
    "anio_2018": 871,
    "anio_2019": 918,
    "anio_2020": 1206,
    "anio_2021": 1096,
    "anio_2022": 933,
    "anio_2023": 990,
    "anio_2024": 873,
    "anio_2025": 636,
    "variacion_porcentaje": -27.15,
    "total_bogota": 4294
},
{
    "codigo_localidad": "10",
    "nombre_localidad": "Engativá",
    "lat": 4.7000,
    "lng": -74.1000,
    "mes": "Ene-Sep (2024vs2025)",
    "tipo": "Hurto a Comercio",
    "anio_2018": 1477,
    "anio_2019": 1421,
    "anio_2020": 957,
    "anio_2021": 721,
    "anio_2022": 767,
    "anio_2023": 925,
    "anio_2024": 686,
    "anio_2025": 598,
    "variacion_porcentaje": -12.83,
    "total_bogota": 6694
},
{
    "codigo_localidad": "10",
    "nombre_localidad": "Engativá",
    "lat": 4.7000,
    "lng": -74.1000,
    "mes": "Ene-Sep (2024vs2025)",
    "tipo": "Hurto de Celulares",
    "anio_2018": 4541,
    "anio_2019": 4054,
    "anio_2020": 3594,
    "anio_2021": 4376,
    "anio_2022": 4466,
    "anio_2023": 4180,
    "anio_2024": 0,
    "anio_2025": 2243,
    "variacion_porcentaje": 0,
    "total_bogota": 24392
},
{
    "codigo_localidad": "10",
    "nombre_localidad": "Engativá",
    "lat": 4.7000,
    "lng": -74.1000,
    "mes": "Ene-Sep (2024vs2025)",
    "tipo": "Hurto de Motocicletas",
    "anio_2018": 344,
    "anio_2019": 334,
    "anio_2020": 230,
    "anio_2021": 387,
    "anio_2022": 410,
    "anio_2023": 485,
    "anio_2024": 482,
    "anio_2025": 392,
    "variacion_porcentaje": -18.67,
    "total_bogota": 3449
},
{
    "codigo_localidad": "10",
    "nombre_localidad": "Engativá",
    "lat": 4.7000,
    "lng": -74.1000,
    "mes": "Ene-Sep (2024vs2025)",
    "tipo": "Delitos Sexuales",
    "anio_2018": 324,
    "anio_2019": 358,
    "anio_2020": 255,
    "anio_2021": 352,
    "anio_2022": 386,
    "anio_2023": 307,
    "anio_2024": 505,
    "anio_2025": 520,
    "variacion_porcentaje": 2.97,
    "total_bogota": 6968
},
{
    "codigo_localidad": "10",
    "nombre_localidad": "Engativá",
    "lat": 4.7000,
    "lng": -74.1000,
    "mes": "Ene-Sep (2024vs2025)",
    "tipo": "Violencia Intrafamiliar",
    "anio_2018": 2439,
    "anio_2019": 2275,
    "anio_2020": 2819,
    "anio_2021": 2415,
    "anio_2022": 2498,
    "anio_2023": 1731,
    "anio_2024": 2768,
    "anio_2025": 3216,
    "variacion_porcentaje": 16.18,
    "total_bogota": 38257
},
{
    "codigo_localidad": "11",
    "nombre_localidad": "Suba",
    "lat": 4.7500,
    "lng": -74.0800,
    "mes": "Ene-Sep (2024vs2025)",
    "tipo": "Homicidios",
    "anio_2018": 67,
    "anio_2019": 61,
    "anio_2020": 55,
    "anio_2021": 43,
    "anio_2022": 56,
    "anio_2023": 56,
    "anio_2024": 56,
    "anio_2025": 65,
    "variacion_porcentaje": 16.07,
    "total_bogota": 875
},
{
    "codigo_localidad": "11",
    "nombre_localidad": "Suba",
    "lat": 4.7500,
    "lng": -74.0800,
    "mes": "Ene-Sep (2024vs2025)",
    "tipo": "Lesiones Personales",
    "anio_2018": 1977,
    "anio_2019": 1389,
    "anio_2020": 1129,
    "anio_2021": 1563,
    "anio_2022": 1556,
    "anio_2023": 1482,
    "anio_2024": 1177,
    "anio_2025": 1380,
    "variacion_porcentaje": 17.25,
    "total_bogota": 15137
},
{
    "codigo_localidad": "11",
    "nombre_localidad": "Suba",
    "lat": 4.7500,
    "lng": -74.0800,
    "mes": "Ene-Sep (2024vs2025)",
    "tipo": "Hurto a Personas",
    "anio_2018": 8107,
    "anio_2019": 9264,
    "anio_2020": 6452,
    "anio_2021": 7708,
    "anio_2022": 9925,
    "anio_2023": 13717,
    "anio_2024": 9671,
    "anio_2025": 9535,
    "variacion_porcentaje": -1.41,
    "total_bogota": 100894
},
{
    "codigo_localidad": "11",
    "nombre_localidad": "Suba",
    "lat": 4.7500,
    "lng": -74.0800,
    "mes": "Ene-Sep (2024vs2025)",
    "tipo": "Hurto a Residencias",
    "anio_2018": 1050,
    "anio_2019": 943,
    "anio_2020": 787,
    "anio_2021": 809,
    "anio_2022": 659,
    "anio_2023": 797,
    "anio_2024": 620,
    "anio_2025": 584,
    "variacion_porcentaje": -5.81,
    "total_bogota": 4701
},
{
    "codigo_localidad": "11",
    "nombre_localidad": "Suba",
    "lat": 4.7500,
    "lng": -74.0800,
    "mes": "Ene-Sep (2024vs2025)",
    "tipo": "Hurto de Automotores",
    "anio_2018": 237,
    "anio_2019": 257,
    "anio_2020": 230,
    "anio_2021": 228,
    "anio_2022": 226,
    "anio_2023": 264,
    "anio_2024": 181,
    "anio_2025": 175,
    "variacion_porcentaje": -3.31,
    "total_bogota": 2401
},
{
    "codigo_localidad": "11",
    "nombre_localidad": "Suba",
    "lat": 4.7500,
    "lng": -74.0800,
    "mes": "Ene-Sep (2024vs2025)",
    "tipo": "Hurto de Bicicletas",
    "anio_2018": 932,
    "anio_2019": 791,
    "anio_2020": 1097,
    "anio_2021": 941,
    "anio_2022": 976,
    "anio_2023": 858,
    "anio_2024": 867,
    "anio_2025": 734,
    "variacion_porcentaje": -15.34,
    "total_bogota": 4294
},
{
    "codigo_localidad": "11",
    "nombre_localidad": "Suba",
    "lat": 4.7500,
    "lng": -74.0800,
    "mes": "Ene-Sep (2024vs2025)",
    "tipo": "Hurto a Comercio",
    "anio_2018": 1509,
    "anio_2019": 1510,
    "anio_2020": 1048,
    "anio_2021": 827,
    "anio_2022": 826,
    "anio_2023": 1052,
    "anio_2024": 863,
    "anio_2025": 755,
    "variacion_porcentaje": -12.51,
    "total_bogota": 6694
},
{
    "codigo_localidad": "11",
    "nombre_localidad": "Suba",
    "lat": 4.7500,
    "lng": -74.0800,
    "mes": "Ene-Sep (2024vs2025)",
    "tipo": "Hurto de Celulares",
    "anio_2018": 5090,
    "anio_2019": 4353,
    "anio_2020": 3673,
    "anio_2021": 4181,
    "anio_2022": 4741,
    "anio_2023": 4817,
    "anio_2024": 0,
    "anio_2025": 2760,
    "variacion_porcentaje": 0,
    "total_bogota": 24392
},
{
    "codigo_localidad": "11",
    "nombre_localidad": "Suba",
    "lat": 4.7500,
    "lng": -74.0800,
    "mes": "Ene-Sep (2024vs2025)",
    "tipo": "Hurto de Motocicletas",
    "anio_2018": 235,
    "anio_2019": 287,
    "anio_2020": 268,
    "anio_2021": 339,
    "anio_2022": 348,
    "anio_2023": 369,
    "anio_2024": 383,
    "anio_2025": 238,
    "variacion_porcentaje": -37.86,
    "total_bogota": 3449
},
{
    "codigo_localidad": "11",
    "nombre_localidad": "Suba",
    "lat": 4.7500,
    "lng": -74.0800,
    "mes": "Ene-Sep (2024vs2025)",
    "tipo": "Delitos Sexuales",
    "anio_2018": 444,
    "anio_2019": 484,
    "anio_2020": 452,
    "anio_2021": 573,
    "anio_2022": 549,
    "anio_2023": 437,
    "anio_2024": 661,
    "anio_2025": 477,
    "variacion_porcentaje": -27.84,
    "total_bogota": 6968
},
{
    "codigo_localidad": "11",
    "nombre_localidad": "Suba",
    "lat": 4.7500,
    "lng": -74.0800,
    "mes": "Ene-Sep (2024vs2025)",
    "tipo": "Violencia Intrafamiliar",
    "anio_2018": 3082,
    "anio_2019": 3327,
    "anio_2020": 3304,
    "anio_2021": 3733,
    "anio_2022": 2850,
    "anio_2023": 2996,
    "anio_2024": 3999,
    "anio_2025": 3098,
    "variacion_porcentaje": -22.53,
    "total_bogota": 38257
},
{
    "codigo_localidad": "12",
    "nombre_localidad": "Barrios Unidos",
    "lat": 4.6700,
    "lng": -74.0800,
    "mes": "Ene-Sep (2024vs2025)",
    "tipo": "Homicidios",
    "anio_2018": 7,
    "anio_2019": 4,
    "anio_2020": 6,
    "anio_2021": 10,
    "anio_2022": 11,
    "anio_2023": 16,
    "anio_2024": 17,
    "anio_2025": 14,
    "variacion_porcentaje": -17.65,
    "total_bogota": 875
},
{
    "codigo_localidad": "12",
    "nombre_localidad": "Barrios Unidos",
    "lat": 4.6700,
    "lng": -74.0800,
    "mes": "Ene-Sep (2024vs2025)",
    "tipo": "Lesiones Personales",
    "anio_2018": 598,
    "anio_2019": 444,
    "anio_2020": 314,
    "anio_2021": 425,
    "anio_2022": 479,
    "anio_2023": 454,
    "anio_2024": 368,
    "anio_2025": 347,
    "variacion_porcentaje": -5.71,
    "total_bogota": 15137
},
{
    "codigo_localidad": "12",
    "nombre_localidad": "Barrios Unidos",
    "lat": 4.6700,
    "lng": -74.0800,
    "mes": "Ene-Sep (2024vs2025)",
    "tipo": "Hurto a Personas",
    "anio_2018": 3368,
    "anio_2019": 4018,
    "anio_2020": 2413,
    "anio_2021": 3027,
    "anio_2022": 3718,
    "anio_2023": 5434,
    "anio_2024": 3939,
    "anio_2025": 3481,
    "variacion_porcentaje": -11.63,
    "total_bogota": 100894
},
{
    "codigo_localidad": "12",
    "nombre_localidad": "Barrios Unidos",
    "lat": 4.6700,
    "lng": -74.0800,
    "mes": "Ene-Sep (2024vs2025)",
    "tipo": "Hurto a Residencias",
    "anio_2018": 248,
    "anio_2019": 229,
    "anio_2020": 224,
    "anio_2021": 200,
    "anio_2022": 191,
    "anio_2023": 167,
    "anio_2024": 170,
    "anio_2025": 158,
    "variacion_porcentaje": -7.06,
    "total_bogota": 4701
},
{
    "codigo_localidad": "12",
    "nombre_localidad": "Barrios Unidos",
    "lat": 4.6700,
    "lng": -74.0800,
    "mes": "Ene-Sep (2024vs2025)",
    "tipo": "Hurto de Automotores",
    "anio_2018": 79,
    "anio_2019": 83,
    "anio_2020": 72,
    "anio_2021": 79,
    "anio_2022": 66,
    "anio_2023": 62,
    "anio_2024": 105,
    "anio_2025": 75,
    "variacion_porcentaje": -28.57,
    "total_bogota": 2401
},
{
    "codigo_localidad": "12",
    "nombre_localidad": "Barrios Unidos",
    "lat": 4.6700,
    "lng": -74.0800,
    "mes": "Ene-Sep (2024vs2025)",
    "tipo": "Hurto de Bicicletas",
    "anio_2018": 319,
    "anio_2019": 277,
    "anio_2020": 296,
    "anio_2021": 316,
    "anio_2022": 223,
    "anio_2023": 282,
    "anio_2024": 257,
    "anio_2025": 174,
    "variacion_porcentaje": -32.30,
    "total_bogota": 4294
},
{
    "codigo_localidad": "12",
    "nombre_localidad": "Barrios Unidos",
    "lat": 4.6700,
    "lng": -74.0800,
    "mes": "Ene-Sep (2024vs2025)",
    "tipo": "Hurto a Comercio",
    "anio_2018": 540,
    "anio_2019": 610,
    "anio_2020": 443,
    "anio_2021": 430,
    "anio_2022": 409,
    "anio_2023": 456,
    "anio_2024": 399,
    "anio_2025": 344,
    "variacion_porcentaje": -13.78,
    "total_bogota": 6694
},
{
    "codigo_localidad": "12",
    "nombre_localidad": "Barrios Unidos",
    "lat": 4.6700,
    "lng": -74.0800,
    "mes": "Ene-Sep (2024vs2025)",
    "tipo": "Hurto de Celulares",
    "anio_2018": 2186,
    "anio_2019": 1898,
    "anio_2020": 1432,
    "anio_2021": 1496,
    "anio_2022": 1668,
    "anio_2023": 1711,
    "anio_2024": 0,
    "anio_2025": 1135,
    "variacion_porcentaje": 0,
    "total_bogota": 24392
},
{
    "codigo_localidad": "12",
    "nombre_localidad": "Barrios Unidos",
    "lat": 4.6700,
    "lng": -74.0800,
    "mes": "Ene-Sep (2024vs2025)",
    "tipo": "Hurto de Motocicletas",
    "anio_2018": 46,
    "anio_2019": 56,
    "anio_2020": 43,
    "anio_2021": 73,
    "anio_2022": 66,
    "anio_2023": 74,
    "anio_2024": 101,
    "anio_2025": 94,
    "variacion_porcentaje": -6.93,
    "total_bogota": 3449
},
{
    "codigo_localidad": "12",
    "nombre_localidad": "Barrios Unidos",
    "lat": 4.6700,
    "lng": -74.0800,
    "mes": "Ene-Sep (2024vs2025)",
    "tipo": "Delitos Sexuales",
    "anio_2018": 74,
    "anio_2019": 79,
    "anio_2020": 68,
    "anio_2021": 103,
    "anio_2022": 174,
    "anio_2023": 91,
    "anio_2024": 154,
    "anio_2025": 139,
    "variacion_porcentaje": -9.74,
    "total_bogota": 6968
},
{
    "codigo_localidad": "12",
    "nombre_localidad": "Barrios Unidos",
    "lat": 4.6700,
    "lng": -74.0800,
    "mes": "Ene-Sep (2024vs2025)",
    "tipo": "Violencia Intrafamiliar",
    "anio_2018": 448,
    "anio_2019": 428,
    "anio_2020": 485,
    "anio_2021": 547,
    "anio_2022": 609,
    "anio_2023": 382,
    "anio_2024": 652,
    "anio_2025": 785,
    "variacion_porcentaje": 20.40,
    "total_bogota": 38257
},
{
    "codigo_localidad": "13",
    "nombre_localidad": "Teusaquillo",
    "lat": 4.6500,
    "lng": -74.0800,
    "mes": "Ene-Sep (2024vs2025)",
    "tipo": "Homicidios",
    "anio_2018": 4,
    "anio_2019": 3,
    "anio_2020": 4,
    "anio_2021": 10,
    "anio_2022": 13,
    "anio_2023": 12,
    "anio_2024": 6,
    "anio_2025": 8,
    "variacion_porcentaje": 33.33,
    "total_bogota": 875
},
{
    "codigo_localidad": "13",
    "nombre_localidad": "Teusaquillo",
    "lat": 4.6500,
    "lng": -74.0800,
    "mes": "Ene-Sep (2024vs2025)",
    "tipo": "Lesiones Personales",
    "anio_2018": 624,
    "anio_2019": 333,
    "anio_2020": 189,
    "anio_2021": 358,
    "anio_2022": 322,
    "anio_2023": 306,
    "anio_2024": 369,
    "anio_2025": 392,
    "variacion_porcentaje": 6.23,
    "total_bogota": 15137
},
{
    "codigo_localidad": "13",
    "nombre_localidad": "Teusaquillo",
    "lat": 4.6500,
    "lng": -74.0800,
    "mes": "Ene-Sep (2024vs2025)",
    "tipo": "Hurto a Personas",
    "anio_2018": 5007,
    "anio_2019": 5952,
    "anio_2020": 2853,
    "anio_2021": 3614,
    "anio_2022": 5298,
    "anio_2023": 8178,
    "anio_2024": 5577,
    "anio_2025": 6604,
    "variacion_porcentaje": 18.41,
    "total_bogota": 100894
},
{
    "codigo_localidad": "13",
    "nombre_localidad": "Teusaquillo",
    "lat": 4.6500,
    "lng": -74.0800,
    "mes": "Ene-Sep (2024vs2025)",
    "tipo": "Hurto a Residencias",
    "anio_2018": 316,
    "anio_2019": 354,
    "anio_2020": 263,
    "anio_2021": 264,
    "anio_2022": 285,
    "anio_2023": 352,
    "anio_2024": 233,
    "anio_2025": 228,
    "variacion_porcentaje": -2.15,
    "total_bogota": 4701
},
{
    "codigo_localidad": "13",
    "nombre_localidad": "Teusaquillo",
    "lat": 4.6500,
    "lng": -74.0800,
    "mes": "Ene-Sep (2024vs2025)",
    "tipo": "Hurto de Automotores",
    "anio_2018": 68,
    "anio_2019": 74,
    "anio_2020": 43,
    "anio_2021": 67,
    "anio_2022": 53,
    "anio_2023": 136,
    "anio_2024": 115,
    "anio_2025": 80,
    "variacion_porcentaje": -30.43,
    "total_bogota": 2401
},
{
    "codigo_localidad": "13",
    "nombre_localidad": "Teusaquillo",
    "lat": 4.6500,
    "lng": -74.0800,
    "mes": "Ene-Sep (2024vs2025)",
    "tipo": "Hurto de Bicicletas",
    "anio_2018": 398,
    "anio_2019": 376,
    "anio_2020": 341,
    "anio_2021": 383,
    "anio_2022": 256,
    "anio_2023": 322,
    "anio_2024": 257,
    "anio_2025": 202,
    "variacion_porcentaje": -21.40,
    "total_bogota": 4294
},
{
    "codigo_localidad": "13",
    "nombre_localidad": "Teusaquillo",
    "lat": 4.6500,
    "lng": -74.0800,
    "mes": "Ene-Sep (2024vs2025)",
    "tipo": "Hurto a Comercio",
    "anio_2018": 903,
    "anio_2019": 742,
    "anio_2020": 482,
    "anio_2021": 418,
    "anio_2022": 479,
    "anio_2023": 438,
    "anio_2024": 409,
    "anio_2025": 393,
    "variacion_porcentaje": -3.91,
    "total_bogota": 6694
},
{
    "codigo_localidad": "13",
    "nombre_localidad": "Teusaquillo",
    "lat": 4.6500,
    "lng": -74.0800,
    "mes": "Ene-Sep (2024vs2025)",
    "tipo": "Hurto de Celulares",
    "anio_2018": 3194,
    "anio_2019": 2933,
    "anio_2020": 1614,
    "anio_2021": 1827,
    "anio_2022": 2869,
    "anio_2023": 2994,
    "anio_2024": 0,
    "anio_2025": 2035,
    "variacion_porcentaje": 0,
    "total_bogota": 24392
},
{
    "codigo_localidad": "13",
    "nombre_localidad": "Teusaquillo",
    "lat": 4.6500,
    "lng": -74.0800,
    "mes": "Ene-Sep (2024vs2025)",
    "tipo": "Hurto de Motocicletas",
    "anio_2018": 37,
    "anio_2019": 39,
    "anio_2020": 24,
    "anio_2021": 43,
    "anio_2022": 52,
    "anio_2023": 90,
    "anio_2024": 112,
    "anio_2025": 88,
    "variacion_porcentaje": -21.43,
    "total_bogota": 3449
},
{
    "codigo_localidad": "13",
    "nombre_localidad": "Teusaquillo",
    "lat": 4.6500,
    "lng": -74.0800,
    "mes": "Ene-Sep (2024vs2025)",
    "tipo": "Delitos Sexuales",
    "anio_2018": 92,
    "anio_2019": 108,
    "anio_2020": 67,
    "anio_2021": 119,
    "anio_2022": 105,
    "anio_2023": 111,
    "anio_2024": 319,
    "anio_2025": 185,
    "variacion_porcentaje": -42.01,
    "total_bogota": 6968
},
{
    "codigo_localidad": "13",
    "nombre_localidad": "Teusaquillo",
    "lat": 4.6500,
    "lng": -74.0800,
    "mes": "Ene-Sep (2024vs2025)",
    "tipo": "Violencia Intrafamiliar",
    "anio_2018": 436,
    "anio_2019": 239,
    "anio_2020": 319,
    "anio_2021": 814,
    "anio_2022": 474,
    "anio_2023": 260,
    "anio_2024": 623,
    "anio_2025": 937,
    "variacion_porcentaje": 50.40,
    "total_bogota": 38257
},
{
    "codigo_localidad": "14",
    "nombre_localidad": "Los Mártires",
    "lat": 4.6000,
    "lng": -74.0800,
    "mes": "Ene-Sep (2024vs2025)",
    "tipo": "Homicidios",
    "anio_2018": 45,
    "anio_2019": 45,
    "anio_2020": 36,
    "anio_2021": 55,
    "anio_2022": 40,
    "anio_2023": 38,
    "anio_2024": 29,
    "anio_2025": 32,
    "variacion_porcentaje": 10.34,
    "total_bogota": 875
},
{
    "codigo_localidad": "14",
    "nombre_localidad": "Los Mártires",
    "lat": 4.6000,
    "lng": -74.0800,
    "mes": "Ene-Sep (2024vs2025)",
    "tipo": "Lesiones Personales",
    "anio_2018": 852,
    "anio_2019": 446,
    "anio_2020": 392,
    "anio_2021": 537,
    "anio_2022": 639,
    "anio_2023": 689,
    "anio_2024": 875,
    "anio_2025": 429,
    "variacion_porcentaje": -50.97,
    "total_bogota": 15137
},
{
    "codigo_localidad": "14",
    "nombre_localidad": "Los Mártires",
    "lat": 4.6000,
    "lng": -74.0800,
    "mes": "Ene-Sep (2024vs2025)",
    "tipo": "Hurto a Personas",
    "anio_2018": 3096,
    "anio_2019": 3941,
    "anio_2020": 2363,
    "anio_2021": 2919,
    "anio_2022": 3758,
    "anio_2023": 5389,
    "anio_2024": 10065,
    "anio_2025": 3944,
    "variacion_porcentaje": -60.81,
    "total_bogota": 100894
},
{
    "codigo_localidad": "14",
    "nombre_localidad": "Los Mártires",
    "lat": 4.6000,
    "lng": -74.0800,
    "mes": "Ene-Sep (2024vs2025)",
    "tipo": "Hurto a Residencias",
    "anio_2018": 114,
    "anio_2019": 123,
    "anio_2020": 156,
    "anio_2021": 161,
    "anio_2022": 123,
    "anio_2023": 136,
    "anio_2024": 146,
    "anio_2025": 81,
    "variacion_porcentaje": -44.52,
    "total_bogota": 4701
},
{
    "codigo_localidad": "14",
    "nombre_localidad": "Los Mártires",
    "lat": 4.6000,
    "lng": -74.0800,
    "mes": "Ene-Sep (2024vs2025)",
    "tipo": "Hurto de Automotores",
    "anio_2018": 64,
    "anio_2019": 70,
    "anio_2020": 59,
    "anio_2021": 65,
    "anio_2022": 52,
    "anio_2023": 44,
    "anio_2024": 109,
    "anio_2025": 53,
    "variacion_porcentaje": -51.38,
    "total_bogota": 2401
},
{
    "codigo_localidad": "14",
    "nombre_localidad": "Los Mártires",
    "lat": 4.6000,
    "lng": -74.0800,
    "mes": "Ene-Sep (2024vs2025)",
    "tipo": "Hurto de Bicicletas",
    "anio_2018": 150,
    "anio_2019": 128,
    "anio_2020": 174,
    "anio_2021": 221,
    "anio_2022": 145,
    "anio_2023": 116,
    "anio_2024": 377,
    "anio_2025": 108,
    "variacion_porcentaje": -71.35,
    "total_bogota": 4294
},
{
    "codigo_localidad": "14",
    "nombre_localidad": "Los Mártires",
    "lat": 4.6000,
    "lng": -74.0800,
    "mes": "Ene-Sep (2024vs2025)",
    "tipo": "Hurto a Comercio",
    "anio_2018": 552,
    "anio_2019": 482,
    "anio_2020": 324,
    "anio_2021": 379,
    "anio_2022": 413,
    "anio_2023": 558,
    "anio_2024": 725,
    "anio_2025": 244,
    "variacion_porcentaje": -66.34,
    "total_bogota": 6694
},
{
    "codigo_localidad": "14",
    "nombre_localidad": "Los Mártires",
    "lat": 4.6000,
    "lng": -74.0800,
    "mes": "Ene-Sep (2024vs2025)",
    "tipo": "Hurto de Celulares",
    "anio_2018": 1965,
    "anio_2019": 1941,
    "anio_2020": 1364,
    "anio_2021": 1844,
    "anio_2022": 1906,
    "anio_2023": 1635,
    "anio_2024": 0,
    "anio_2025": 1038,
    "variacion_porcentaje": 0,
    "total_bogota": 24392
},
{
    "codigo_localidad": "14",
    "nombre_localidad": "Los Mártires",
    "lat": 4.6000,
    "lng": -74.0800,
    "mes": "Ene-Sep (2024vs2025)",
    "tipo": "Hurto de Motocicletas",
    "anio_2018": 54,
    "anio_2019": 58,
    "anio_2020": 52,
    "anio_2021": 82,
    "anio_2022": 112,
    "anio_2023": 122,
    "anio_2024": 142,
    "anio_2025": 98,
    "variacion_porcentaje": -30.99,
    "total_bogota": 3449
},
{
    "codigo_localidad": "14",
    "nombre_localidad": "Los Mártires",
    "lat": 4.6000,
    "lng": -74.0800,
    "mes": "Ene-Sep (2024vs2025)",
    "tipo": "Delitos Sexuales",
    "anio_2018": 90,
    "anio_2019": 107,
    "anio_2020": 114,
    "anio_2021": 153,
    "anio_2022": 261,
    "anio_2023": 310,
    "anio_2024": 878,
    "anio_2025": 207,
    "variacion_porcentaje": -76.42,
    "total_bogota": 6968
},
{
    "codigo_localidad": "14",
    "nombre_localidad": "Los Mártires",
    "lat": 4.6000,
    "lng": -74.0800,
    "mes": "Ene-Sep (2024vs2025)",
    "tipo": "Violencia Intrafamiliar",
    "anio_2018": 385,
    "anio_2019": 336,
    "anio_2020": 401,
    "anio_2021": 449,
    "anio_2022": 641,
    "anio_2023": 826,
    "anio_2024": 3381,
    "anio_2025": 673,
    "variacion_porcentaje": -80.09,
    "total_bogota": 38257
},
{
    "codigo_localidad": "15",
    "nombre_localidad": "Antonio Nariño",
    "lat": 4.6000,
    "lng": -74.1500,
    "mes": "Ene-Sep (2024vs2025)",
    "tipo": "Homicidios",
    "anio_2018": 12,
    "anio_2019": 7,
    "anio_2020": 8,
    "anio_2021": 12,
    "anio_2022": 14,
    "anio_2023": 12,
    "anio_2024": 8,
    "anio_2025": 7,
    "variacion_porcentaje": -12.50,
    "total_bogota": 875
},
{
    "codigo_localidad": "15",
    "nombre_localidad": "Antonio Nariño",
    "lat": 4.6000,
    "lng": -74.1500,
    "mes": "Ene-Sep (2024vs2025)",
    "tipo": "Lesiones Personales",
    "anio_2018": 411,
    "anio_2019": 340,
    "anio_2020": 182,
    "anio_2021": 327,
    "anio_2022": 281,
    "anio_2023": 216,
    "anio_2024": 260,
    "anio_2025": 186,
    "variacion_porcentaje": -28.46,
    "total_bogota": 15137
},
{
    "codigo_localidad": "15",
    "nombre_localidad": "Antonio Nariño",
    "lat": 4.6000,
    "lng": -74.1500,
    "mes": "Ene-Sep (2024vs2025)",
    "tipo": "Hurto a Personas",
    "anio_2018": 1284,
    "anio_2019": 1748,
    "anio_2020": 1311,
    "anio_2021": 1835,
    "anio_2022": 1990,
    "anio_2023": 2489,
    "anio_2024": 1694,
    "anio_2025": 1669,
    "variacion_porcentaje": -1.48,
    "total_bogota": 100894
},
{
    "codigo_localidad": "15",
    "nombre_localidad": "Antonio Nariño",
    "lat": 4.6000,
    "lng": -74.1500,
    "mes": "Ene-Sep (2024vs2025)",
    "tipo": "Hurto a Residencias",
    "anio_2018": 108,
    "anio_2019": 115,
    "anio_2020": 133,
    "anio_2021": 118,
    "anio_2022": 74,
    "anio_2023": 92,
    "anio_2024": 59,
    "anio_2025": 62,
    "variacion_porcentaje": 5.08,
    "total_bogota": 4701
},
{
    "codigo_localidad": "15",
    "nombre_localidad": "Antonio Nariño",
    "lat": 4.6000,
    "lng": -74.1500,
    "mes": "Ene-Sep (2024vs2025)",
    "tipo": "Hurto de Automotores",
    "anio_2018": 87,
    "anio_2019": 86,
    "anio_2020": 89,
    "anio_2021": 79,
    "anio_2022": 71,
    "anio_2023": 97,
    "anio_2024": 98,
    "anio_2025": 56,
    "variacion_porcentaje": -42.86,
    "total_bogota": 2401
},
{
    "codigo_localidad": "15",
    "nombre_localidad": "Antonio Nariño",
    "lat": 4.6000,
    "lng": -74.1500,
    "mes": "Ene-Sep (2024vs2025)",
    "tipo": "Hurto de Bicicletas",
    "anio_2018": 87,
    "anio_2019": 66,
    "anio_2020": 146,
    "anio_2021": 111,
    "anio_2022": 116,
    "anio_2023": 75,
    "anio_2024": 69,
    "anio_2025": 66,
    "variacion_porcentaje": -4.35,
    "total_bogota": 4294
},
{
    "codigo_localidad": "15",
    "nombre_localidad": "Antonio Nariño",
    "lat": 4.6000,
    "lng": -74.1500,
    "mes": "Ene-Sep (2024vs2025)",
    "tipo": "Hurto a Comercio",
    "anio_2018": 508,
    "anio_2019": 531,
    "anio_2020": 301,
    "anio_2021": 347,
    "anio_2022": 326,
    "anio_2023": 281,
    "anio_2024": 279,
    "anio_2025": 200,
    "variacion_porcentaje": -28.32,
    "total_bogota": 6694
},
{
    "codigo_localidad": "15",
    "nombre_localidad": "Antonio Nariño",
    "lat": 4.6000,
    "lng": -74.1500,
    "mes": "Ene-Sep (2024vs2025)",
    "tipo": "Hurto de Celulares",
    "anio_2018": 865,
    "anio_2019": 888,
    "anio_2020": 782,
    "anio_2021": 1068,
    "anio_2022": 956,
    "anio_2023": 891,
    "anio_2024": 0,
    "anio_2025": 503,
    "variacion_porcentaje": 0,
    "total_bogota": 24392
},
{
    "codigo_localidad": "15",
    "nombre_localidad": "Antonio Nariño",
    "lat": 4.6000,
    "lng": -74.1500,
    "mes": "Ene-Sep (2024vs2025)",
    "tipo": "Hurto de Motocicletas",
    "anio_2018": 40,
    "anio_2019": 66,
    "anio_2020": 65,
    "anio_2021": 69,
    "anio_2022": 75,
    "anio_2023": 62,
    "anio_2024": 121,
    "anio_2025": 94,
    "variacion_porcentaje": -22.31,
    "total_bogota": 3449
},
{
    "codigo_localidad": "15",
    "nombre_localidad": "Antonio Nariño",
    "lat": 4.6000,
    "lng": -74.1500,
    "mes": "Ene-Sep (2024vs2025)",
    "tipo": "Delitos Sexuales",
    "anio_2018": 54,
    "anio_2019": 56,
    "anio_2020": 42,
    "anio_2021": 77,
    "anio_2022": 76,
    "anio_2023": 58,
    "anio_2024": 113,
    "anio_2025": 77,
    "variacion_porcentaje": -31.86,
    "total_bogota": 6968
},
{
    "codigo_localidad": "15",
    "nombre_localidad": "Antonio Nariño",
    "lat": 4.6000,
    "lng": -74.1500,
    "mes": "Ene-Sep (2024vs2025)",
    "tipo": "Violencia Intrafamiliar",
    "anio_2018": 351,
    "anio_2019": 318,
    "anio_2020": 361,
    "anio_2021": 336,
    "anio_2022": 384,
    "anio_2023": 315,
    "anio_2024": 271,
    "anio_2025": 329,
    "variacion_porcentaje": 21.40,
    "total_bogota": 38257
},
{
    "codigo_localidad": "16",
    "nombre_localidad": "Puente Aranda",
    "lat": 4.6300,
    "lng": -74.1400,
    "mes": "Ene-Sep (2024vs2025)",
    "tipo": "Homicidios",
    "anio_2018": 18,
    "anio_2019": 24,
    "anio_2020": 37,
    "anio_2021": 16,
    "anio_2022": 15,
    "anio_2023": 9,
    "anio_2024": 19,
    "anio_2025": 28,
    "variacion_porcentaje": 47.37,
    "total_bogota": 875
},
{
    "codigo_localidad": "16",
    "nombre_localidad": "Puente Aranda",
    "lat": 4.6300,
    "lng": -74.1400,
    "mes": "Ene-Sep (2024vs2025)",
    "tipo": "Lesiones Personales",
    "anio_2018": 1016,
    "anio_2019": 748,
    "anio_2020": 470,
    "anio_2021": 645,
    "anio_2022": 708,
    "anio_2023": 647,
    "anio_2024": 541,
    "anio_2025": 623,
    "variacion_porcentaje": 15.16,
    "total_bogota": 15137
},
{
    "codigo_localidad": "16",
    "nombre_localidad": "Puente Aranda",
    "lat": 4.6300,
    "lng": -74.1400,
    "mes": "Ene-Sep (2024vs2025)",
    "tipo": "Hurto a Personas",
    "anio_2018": 3320,
    "anio_2019": 4132,
    "anio_2020": 3081,
    "anio_2021": 3884,
    "anio_2022": 4618,
    "anio_2023": 5400,
    "anio_2024": 4002,
    "anio_2025": 5087,
    "variacion_porcentaje": 27.11,
    "total_bogota": 100894
},
{
    "codigo_localidad": "16",
    "nombre_localidad": "Puente Aranda",
    "lat": 4.6300,
    "lng": -74.1400,
    "mes": "Ene-Sep (2024vs2025)",
    "tipo": "Hurto a Residencias",
    "anio_2018": 353,
    "anio_2019": 295,
    "anio_2020": 343,
    "anio_2021": 321,
    "anio_2022": 230,
    "anio_2023": 249,
    "anio_2024": 190,
    "anio_2025": 198,
    "variacion_porcentaje": 4.21,
    "total_bogota": 4701
},
{
    "codigo_localidad": "16",
    "nombre_localidad": "Puente Aranda",
    "lat": 4.6300,
    "lng": -74.1400,
    "mes": "Ene-Sep (2024vs2025)",
    "tipo": "Hurto de Automotores",
    "anio_2018": 300,
    "anio_2019": 270,
    "anio_2020": 228,
    "anio_2021": 213,
    "anio_2022": 241,
    "anio_2023": 247,
    "anio_2024": 303,
    "anio_2025": 288,
    "variacion_porcentaje": -4.95,
    "total_bogota": 2401
},
{
    "codigo_localidad": "16",
    "nombre_localidad": "Puente Aranda",
    "lat": 4.6300,
    "lng": -74.1400,
    "mes": "Ene-Sep (2024vs2025)",
    "tipo": "Hurto de Bicicletas",
    "anio_2018": 251,
    "anio_2019": 184,
    "anio_2020": 370,
    "anio_2021": 323,
    "anio_2022": 269,
    "anio_2023": 230,
    "anio_2024": 200,
    "anio_2025": 181,
    "variacion_porcentaje": -9.50,
    "total_bogota": 4294
},
{
    "codigo_localidad": "16",
    "nombre_localidad": "Puente Aranda",
    "lat": 4.6300,
    "lng": -74.1400,
    "mes": "Ene-Sep (2024vs2025)",
    "tipo": "Hurto a Comercio",
    "anio_2018": 978,
    "anio_2019": 944,
    "anio_2020": 477,
    "anio_2021": 562,
    "anio_2022": 535,
    "anio_2023": 520,
    "anio_2024": 510,
    "anio_2025": 418,
    "variacion_porcentaje": -18.04,
    "total_bogota": 6694
},
{
    "codigo_localidad": "16",
    "nombre_localidad": "Puente Aranda",
    "lat": 4.6300,
    "lng": -74.1400,
    "mes": "Ene-Sep (2024vs2025)",
    "tipo": "Hurto de Celulares",
    "anio_2018": 2148,
    "anio_2019": 1897,
    "anio_2020": 1856,
    "anio_2021": 2037,
    "anio_2022": 2274,
    "anio_2023": 1764,
    "anio_2024": 0,
    "anio_2025": 1096,
    "variacion_porcentaje": 0,
    "total_bogota": 24392
},
{
    "codigo_localidad": "16",
    "nombre_localidad": "Puente Aranda",
    "lat": 4.6300,
    "lng": -74.1400,
    "mes": "Ene-Sep (2024vs2025)",
    "tipo": "Hurto de Motocicletas",
    "anio_2018": 130,
    "anio_2019": 165,
    "anio_2020": 99,
    "anio_2021": 182,
    "anio_2022": 211,
    "anio_2023": 193,
    "anio_2024": 200,
    "anio_2025": 171,
    "variacion_porcentaje": -14.50,
    "total_bogota": 3449
},
{
    "codigo_localidad": "16",
    "nombre_localidad": "Puente Aranda",
    "lat": 4.6300,
    "lng": -74.1400,
    "mes": "Ene-Sep (2024vs2025)",
    "tipo": "Delitos Sexuales",
    "anio_2018": 160,
    "anio_2019": 228,
    "anio_2020": 121,
    "anio_2021": 162,
    "anio_2022": 230,
    "anio_2023": 215,
    "anio_2024": 217,
    "anio_2025": 281,
    "variacion_porcentaje": 29.49,
    "total_bogota": 6968
},
{
    "codigo_localidad": "16",
    "nombre_localidad": "Puente Aranda",
    "lat": 4.6300,
    "lng": -74.1400,
    "mes": "Ene-Sep (2024vs2025)",
    "tipo": "Violencia Intrafamiliar",
    "anio_2018": 779,
    "anio_2019": 879,
    "anio_2020": 841,
    "anio_2021": 1311,
    "anio_2022": 782,
    "anio_2023": 758,
    "anio_2024": 623,
    "anio_2025": 1583,
    "variacion_porcentaje": 154.09,
    "total_bogota": 38257
},
{
    "codigo_localidad": "17",
    "nombre_localidad": "Candelaria",
    "lat": 4.5981,
    "lng": -74.0758,
    "mes": "Ene-Sep (2024vs2025)",
    "tipo": "Homicidios",
    "anio_2018": 3,
    "anio_2019": 1,
    "anio_2020": 2,
    "anio_2021": 6,
    "anio_2022": 2,
    "anio_2023": 5,
    "anio_2024": 3,
    "anio_2025": 1,
    "variacion_porcentaje": -66.67,
    "total_bogota": 875
},
{
    "codigo_localidad": "17",
    "nombre_localidad": "Candelaria",
    "lat": 4.5981,
    "lng": -74.0758,
    "mes": "Ene-Sep (2024vs2025)",
    "tipo": "Lesiones Personales",
    "anio_2018": 180,
    "anio_2019": 208,
    "anio_2020": 149,
    "anio_2021": 252,
    "anio_2022": 152,
    "anio_2023": 144,
    "anio_2024": 142,
    "anio_2025": 122,
    "variacion_porcentaje": -14.08,
    "total_bogota": 15137
},
{
    "codigo_localidad": "17",
    "nombre_localidad": "Candelaria",
    "lat": 4.5981,
    "lng": -74.0758,
    "mes": "Ene-Sep (2024vs2025)",
    "tipo": "Hurto a Personas",
    "anio_2018": 1161,
    "anio_2019": 1227,
    "anio_2020": 567,
    "anio_2021": 684,
    "anio_2022": 861,
    "anio_2023": 870,
    "anio_2024": 1163,
    "anio_2025": 1193,
    "variacion_porcentaje": 2.58,
    "total_bogota": 100894
},
{
    "codigo_localidad": "17",
    "nombre_localidad": "Candelaria",
    "lat": 4.5981,
    "lng": -74.0758,
    "mes": "Ene-Sep (2024vs2025)",
    "tipo": "Hurto a Residencias",
    "anio_2018": 34,
    "anio_2019": 30,
    "anio_2020": 29,
    "anio_2021": 25,
    "anio_2022": 22,
    "anio_2023": 26,
    "anio_2024": 28,
    "anio_2025": 20,
    "variacion_porcentaje": -28.57,
    "total_bogota": 4701
},
{
    "codigo_localidad": "17",
    "nombre_localidad": "Candelaria",
    "lat": 4.5981,
    "lng": -74.0758,
    "mes": "Ene-Sep (2024vs2025)",
    "tipo": "Hurto de Automotores",
    "anio_2018": 5,
    "anio_2019": 29,
    "anio_2020": 13,
    "anio_2021": 8,
    "anio_2022": 16,
    "anio_2023": 6,
    "anio_2024": 14,
    "anio_2025": 5,
    "variacion_porcentaje": -64.29,
    "total_bogota": 2401
},
{
    "codigo_localidad": "17",
    "nombre_localidad": "Candelaria",
    "lat": 4.5981,
    "lng": -74.0758,
    "mes": "Ene-Sep (2024vs2025)",
    "tipo": "Hurto de Bicicletas",
    "anio_2018": 16,
    "anio_2019": 25,
    "anio_2020": 33,
    "anio_2021": 32,
    "anio_2022": 8,
    "anio_2023": 8,
    "anio_2024": 23,
    "anio_2025": 27,
    "variacion_porcentaje": 17.39,
    "total_bogota": 4294
},
{
    "codigo_localidad": "17",
    "nombre_localidad": "Candelaria",
    "lat": 4.5981,
    "lng": -74.0758,
    "mes": "Ene-Sep (2024vs2025)",
    "tipo": "Hurto a Comercio",
    "anio_2018": 124,
    "anio_2019": 231,
    "anio_2020": 116,
    "anio_2021": 139,
    "anio_2022": 140,
    "anio_2023": 135,
    "anio_2024": 146,
    "anio_2025": 134,
    "variacion_porcentaje": -8.22,
    "total_bogota": 6694
},
{
    "codigo_localidad": "17",
    "nombre_localidad": "Candelaria",
    "lat": 4.5981,
    "lng": -74.0758,
    "mes": "Ene-Sep (2024vs2025)",
    "tipo": "Hurto de Celulares",
    "anio_2018": 676,
    "anio_2019": 461,
    "anio_2020": 316,
    "anio_2021": 338,
    "anio_2022": 403,
    "anio_2023": 263,
    "anio_2024": 0,
    "anio_2025": 368,
    "variacion_porcentaje": 0,
    "total_bogota": 24392
},
{
    "codigo_localidad": "17",
    "nombre_localidad": "Candelaria",
    "lat": 4.5981,
    "lng": -74.0758,
    "mes": "Ene-Sep (2024vs2025)",
    "tipo": "Hurto de Motocicletas",
    "anio_2018": 4,
    "anio_2019": 3,
    "anio_2020": 10,
    "anio_2021": 8,
    "anio_2022": 8,
    "anio_2023": 11,
    "anio_2024": 7,
    "anio_2025": 12,
    "variacion_porcentaje": 71.43,
    "total_bogota": 3449
},
{
    "codigo_localidad": "17",
    "nombre_localidad": "Candelaria",
    "lat": 4.5981,
    "lng": -74.0758,
    "mes": "Ene-Sep (2024vs2025)",
    "tipo": "Delitos Sexuales",
    "anio_2018": 40,
    "anio_2019": 165,
    "anio_2020": 106,
    "anio_2021": 198,
    "anio_2022": 98,
    "anio_2023": 34,
    "anio_2024": 99,
    "anio_2025": 51,
    "variacion_porcentaje": -48.48,
    "total_bogota": 6968
},
{
    "codigo_localidad": "17",
    "nombre_localidad": "Candelaria",
    "lat": 4.5981,
    "lng": -74.0758,
    "mes": "Ene-Sep (2024vs2025)",
    "tipo": "Violencia Intrafamiliar",
    "anio_2018": 90,
    "anio_2019": 128,
    "anio_2020": 203,
    "anio_2021": 235,
    "anio_2022": 626,
    "anio_2023": 108,
    "anio_2024": 183,
    "anio_2025": 123,
    "variacion_porcentaje": -32.79,
    "total_bogota": 38257
},
{
    "codigo_localidad": "18",
    "nombre_localidad": "Rafael Uribe Uribe",
    "lat": 4.6001,
    "lng": -74.1235,
    "mes": "Ene-Sep (2024vs2025)",
    "tipo": "Homicidios",
    "anio_2018": 53,
    "anio_2019": 43,
    "anio_2020": 70,
    "anio_2021": 69,
    "anio_2022": 61,
    "anio_2023": 62,
    "anio_2024": 38,
    "anio_2025": 57,
    "variacion_porcentaje": 50,
    "total_bogota": 875
},
{
    "codigo_localidad": "18",
    "nombre_localidad": "Rafael Uribe Uribe",
    "lat": 4.6001,
    "lng": -74.1235,
    "mes": "Ene-Sep (2024vs2025)",
    "tipo": "Lesiones Personales",
    "anio_2018": 1203,
    "anio_2019": 1139,
    "anio_2020": 792,
    "anio_2021": 958,
    "anio_2022": 770,
    "anio_2023": 771,
    "anio_2024": 795,
    "anio_2025": 653,
    "variacion_porcentaje": -17.86,
    "total_bogota": 15137
},
{
    "codigo_localidad": "18",
    "nombre_localidad": "Rafael Uribe Uribe",
    "lat": 4.6001,
    "lng": -74.1235,
    "mes": "Ene-Sep (2024vs2025)",
    "tipo": "Hurto a Personas",
    "anio_2018": 2419,
    "anio_2019": 2965,
    "anio_2020": 2123,
    "anio_2021": 2877,
    "anio_2022": 3085,
    "anio_2023": 4341,
    "anio_2024": 2531,
    "anio_2025": 2857,
    "variacion_porcentaje": 12.88,
    "total_bogota": 100894
},
{
    "codigo_localidad": "18",
    "nombre_localidad": "Rafael Uribe Uribe",
    "lat": 4.6001,
    "lng": -74.1235,
    "mes": "Ene-Sep (2024vs2025)",
    "tipo": "Hurto a Residencias",
    "anio_2018": 383,
    "anio_2019": 331,
    "anio_2020": 266,
    "anio_2021": 249,
    "anio_2022": 210,
    "anio_2023": 292,
    "anio_2024": 215,
    "anio_2025": 160,
    "variacion_porcentaje": -25.58,
    "total_bogota": 4701
},
{
    "codigo_localidad": "18",
    "nombre_localidad": "Rafael Uribe Uribe",
    "lat": 4.6001,
    "lng": -74.1235,
    "mes": "Ene-Sep (2024vs2025)",
    "tipo": "Hurto de Automotores",
    "anio_2018": 135,
    "anio_2019": 134,
    "anio_2020": 133,
    "anio_2021": 113,
    "anio_2022": 123,
    "anio_2023": 236,
    "anio_2024": 208,
    "anio_2025": 144,
    "variacion_porcentaje": -30.77,
    "total_bogota": 2401
},
{
    "codigo_localidad": "18",
    "nombre_localidad": "Rafael Uribe Uribe",
    "lat": 4.6001,
    "lng": -74.1235,
    "mes": "Ene-Sep (2024vs2025)",
    "tipo": "Hurto de Bicicletas",
    "anio_2018": 119,
    "anio_2019": 115,
    "anio_2020": 196,
    "anio_2021": 169,
    "anio_2022": 148,
    "anio_2023": 121,
    "anio_2024": 101,
    "anio_2025": 69,
    "variacion_porcentaje": -31.68,
    "total_bogota": 4294
},
{
    "codigo_localidad": "18",
    "nombre_localidad": "Rafael Uribe Uribe",
    "lat": 4.6001,
    "lng": -74.1235,
    "mes": "Ene-Sep (2024vs2025)",
    "tipo": "Hurto a Comercio",
    "anio_2018": 366,
    "anio_2019": 392,
    "anio_2020": 298,
    "anio_2021": 400,
    "anio_2022": 230,
    "anio_2023": 353,
    "anio_2024": 261,
    "anio_2025": 162,
    "variacion_porcentaje": -37.93,
    "total_bogota": 6694
},
{
    "codigo_localidad": "18",
    "nombre_localidad": "Rafael Uribe Uribe",
    "lat": 4.6001,
    "lng": -74.1235,
    "mes": "Ene-Sep (2024vs2025)",
    "tipo": "Hurto de Celulares",
    "anio_2018": 1573,
    "anio_2019": 1439,
    "anio_2020": 1335,
    "anio_2021": 1686,
    "anio_2022": 1481,
    "anio_2023": 1387,
    "anio_2024": 0,
    "anio_2025": 680,
    "variacion_porcentaje": 0,
    "total_bogota": 24392
},
{
    "codigo_localidad": "18",
    "nombre_localidad": "Rafael Uribe Uribe",
    "lat": 4.6001,
    "lng": -74.1235,
    "mes": "Ene-Sep (2024vs2025)",
    "tipo": "Hurto de Motocicletas",
    "anio_2018": 171,
    "anio_2019": 214,
    "anio_2020": 115,
    "anio_2021": 243,
    "anio_2022": 215,
    "anio_2023": 235,
    "anio_2024": 248,
    "anio_2025": 201,
    "variacion_porcentaje": -18.95,
    "total_bogota": 3449
},
{
    "codigo_localidad": "18",
    "nombre_localidad": "Rafael Uribe Uribe",
    "lat": 4.6001,
    "lng": -74.1235,
    "mes": "Ene-Sep (2024vs2025)",
    "tipo": "Delitos Sexuales",
    "anio_2018": 207,
    "anio_2019": 273,
    "anio_2020": 173,
    "anio_2021": 181,
    "anio_2022": 263,
    "anio_2023": 200,
    "anio_2024": 417,
    "anio_2025": 230,
    "variacion_porcentaje": -44.84,
    "total_bogota": 6968
},
{
    "codigo_localidad": "18",
    "nombre_localidad": "Rafael Uribe Uribe",
    "lat": 4.6001,
    "lng": -74.1235,
    "mes": "Ene-Sep (2024vs2025)",
    "tipo": "Violencia Intrafamiliar",
    "anio_2018": 1055,
    "anio_2019": 1366,
    "anio_2020": 1278,
    "anio_2021": 1249,
    "anio_2022": 1132,
    "anio_2023": 1021,
    "anio_2024": 1225,
    "anio_2025": 1345,
    "variacion_porcentaje": 9.80,
    "total_bogota": 38257
},
{
    "codigo_localidad": "19",
    "nombre_localidad": "Ciudad Bolívar",
    "lat": 4.5693,
    "lng": -74.1705,
    "mes": "Ene-Sep (2024vs2025)",
    "tipo": "Homicidios",
    "anio_2018": 180,
    "anio_2019": 142,
    "anio_2020": 159,
    "anio_2021": 155,
    "anio_2022": 144,
    "anio_2023": 144,
    "anio_2024": 159,
    "anio_2025": 184,
    "variacion_porcentaje": 15.72,
    "total_bogota": 875
},
{
    "codigo_localidad": "19",
    "nombre_localidad": "Ciudad Bolívar",
    "lat": 4.5693,
    "lng": -74.1705,
    "mes": "Ene-Sep (2024vs2025)",
    "tipo": "Lesiones Personales",
    "anio_2018": 1732,
    "anio_2019": 1816,
    "anio_2020": 1193,
    "anio_2021": 1602,
    "anio_2022": 1398,
    "anio_2023": 1530,
    "anio_2024": 1752,
    "anio_2025": 1302,
    "variacion_porcentaje": -25.68,
    "total_bogota": 15137
},
{
    "codigo_localidad": "19",
    "nombre_localidad": "Ciudad Bolívar",
    "lat": 4.5693,
    "lng": -74.1705,
    "mes": "Ene-Sep (2024vs2025)",
    "tipo": "Hurto a Personas",
    "anio_2018": 2337,
    "anio_2019": 3014,
    "anio_2020": 2586,
    "anio_2021": 3704,
    "anio_2022": 3822,
    "anio_2023": 5320,
    "anio_2024": 3645,
    "anio_2025": 3716,
    "variacion_porcentaje": 1.95,
    "total_bogota": 100894
},
{
    "codigo_localidad": "19",
    "nombre_localidad": "Ciudad Bolívar",
    "lat": 4.5693,
    "lng": -74.1705,
    "mes": "Ene-Sep (2024vs2025)",
    "tipo": "Hurto a Residencias",
    "anio_2018": 404,
    "anio_2019": 438,
    "anio_2020": 323,
    "anio_2021": 306,
    "anio_2022": 292,
    "anio_2023": 339,
    "anio_2024": 278,
    "anio_2025": 217,
    "variacion_porcentaje": -21.94,
    "total_bogota": 4701
},
{
    "codigo_localidad": "19",
    "nombre_localidad": "Ciudad Bolívar",
    "lat": 4.5693,
    "lng": -74.1705,
    "mes": "Ene-Sep (2024vs2025)",
    "tipo": "Hurto de Automotores",
    "anio_2018": 155,
    "anio_2019": 125,
    "anio_2020": 168,
    "anio_2021": 196,
    "anio_2022": 220,
    "anio_2023": 270,
    "anio_2024": 288,
    "anio_2025": 168,
    "variacion_porcentaje": -41.67,
    "total_bogota": 2401
},
{
    "codigo_localidad": "19",
    "nombre_localidad": "Ciudad Bolívar",
    "lat": 4.5693,
    "lng": -74.1705,
    "mes": "Ene-Sep (2024vs2025)",
    "tipo": "Hurto de Bicicletas",
    "anio_2018": 122,
    "anio_2019": 140,
    "anio_2020": 240,
    "anio_2021": 244,
    "anio_2022": 176,
    "anio_2023": 220,
    "anio_2024": 165,
    "anio_2025": 81,
    "variacion_porcentaje": -50.91,
    "total_bogota": 4294
},
{
    "codigo_localidad": "19",
    "nombre_localidad": "Ciudad Bolívar",
    "lat": 4.5693,
    "lng": -74.1705,
    "mes": "Ene-Sep (2024vs2025)",
    "tipo": "Hurto a Comercio",
    "anio_2018": 382,
    "anio_2019": 402,
    "anio_2020": 265,
    "anio_2021": 323,
    "anio_2022": 297,
    "anio_2023": 377,
    "anio_2024": 314,
    "anio_2025": 204,
    "variacion_porcentaje": -35.03,
    "total_bogota": 6694
},
{
    "codigo_localidad": "19",
    "nombre_localidad": "Ciudad Bolívar",
    "lat": 4.5693,
    "lng": -74.1705,
    "mes": "Ene-Sep (2024vs2025)",
    "tipo": "Hurto de Celulares",
    "anio_2018": 1647,
    "anio_2019": 1533,
    "anio_2020": 1713,
    "anio_2021": 2217,
    "anio_2022": 1895,
    "anio_2023": 1658,
    "anio_2024": 0,
    "anio_2025": 816,
    "variacion_porcentaje": 0,
    "total_bogota": 24392
},
{
    "codigo_localidad": "19",
    "nombre_localidad": "Ciudad Bolívar",
    "lat": 4.5693,
    "lng": -74.1705,
    "mes": "Ene-Sep (2024vs2025)",
    "tipo": "Hurto de Motocicletas",
    "anio_2018": 359,
    "anio_2019": 283,
    "anio_2020": 257,
    "anio_2021": 465,
    "anio_2022": 479,
    "anio_2023": 586,
    "anio_2024": 541,
    "anio_2025": 387,
    "variacion_porcentaje": -28.47,
    "total_bogota": 3449
},
{
    "codigo_localidad": "19",
    "nombre_localidad": "Ciudad Bolívar",
    "lat": 4.5693,
    "lng": -74.1705,
    "mes": "Ene-Sep (2024vs2025)",
    "tipo": "Delitos Sexuales",
    "anio_2018": 408,
    "anio_2019": 478,
    "anio_2020": 383,
    "anio_2021": 490,
    "anio_2022": 509,
    "anio_2023": 712,
    "anio_2024": 772,
    "anio_2025": 636,
    "variacion_porcentaje": -17.62,
    "total_bogota": 6968
},
{
    "codigo_localidad": "19",
    "nombre_localidad": "Ciudad Bolívar",
    "lat": 4.5693,
    "lng": -74.1705,
    "mes": "Ene-Sep (2024vs2025)",
    "tipo": "Violencia Intrafamiliar",
    "anio_2018": 3322,
    "anio_2019": 2808,
    "anio_2020": 3074,
    "anio_2021": 2417,
    "anio_2022": 2805,
    "anio_2023": 4146,
    "anio_2024": 3140,
    "anio_2025": 3343,
    "variacion_porcentaje": 6.46,
    "total_bogota": 38257
},
{
    "codigo_localidad": "20",
    "nombre_localidad": "Sumapaz",
    "lat": 4.3367,
    "lng": -74.3236,
    "mes": "Ene-Sep (2024vs2025)",
    "tipo": "Homicidios",
    "anio_2018": 0,
    "anio_2019": 0,
    "anio_2020": 1,
    "anio_2021": 2,
    "anio_2022": 1,
    "anio_2023": 3,
    "anio_2024": 1,
    "anio_2025": 0,
    "variacion_porcentaje": 0,
    "total_bogota": 875
},
{
    "codigo_localidad": "20",
    "nombre_localidad": "Sumapaz",
    "lat": 4.3367,
    "lng": -74.3236,
    "mes": "Ene-Sep (2024vs2025)",
    "tipo": "Lesiones Personales",
    "anio_2018": 16,
    "anio_2019": 0,
    "anio_2020": 7,
    "anio_2021": 1,
    "anio_2022": 0,
    "anio_2023": 0,
    "anio_2024": 0,
    "anio_2025": 0,
    "variacion_porcentaje": 0,
    "total_bogota": 15137
},
{
    "codigo_localidad": "20",
    "nombre_localidad": "Sumapaz",
    "lat": 4.3367,
    "lng": -74.3236,
    "mes": "Ene-Sep (2024vs2025)",
    "tipo": "Hurto a Personas",
    "anio_2018": 0,
    "anio_2019": 0,
    "anio_2020": 0,
    "anio_2021": 0,
    "anio_2022": 0,
    "anio_2023": 0,
    "anio_2024": 0,
    "anio_2025": 0,
    "variacion_porcentaje": 0,
    "total_bogota": 100894
},
{
    "codigo_localidad": "20",
    "nombre_localidad": "Sumapaz",
    "lat": 4.3367,
    "lng": -74.3236,
    "mes": "Ene-Sep (2024vs2025)",
    "tipo": "Hurto a Residencias",
    "anio_2018": 0,
    "anio_2019": 0,
    "anio_2020": 0,
    "anio_2021": 0,
    "anio_2022": 0,
    "anio_2023": 0,
    "anio_2024": 0,
    "anio_2025": 0,
    "variacion_porcentaje": 0,
    "total_bogota": 4701
},
{
    "codigo_localidad": "20",
    "nombre_localidad": "Sumapaz",
    "lat": 4.3367,
    "lng": -74.3236,
    "mes": "Ene-Sep (2024vs2025)",
    "tipo": "Hurto de Automotores",
    "anio_2018": 0,
    "anio_2019": 0,
    "anio_2020": 0,
    "anio_2021": 0,
    "anio_2022": 0,
    "anio_2023": 0,
    "anio_2024": 0,
    "anio_2025": 0,
    "variacion_porcentaje": 0,
    "total_bogota": 2401
},
{
    "codigo_localidad": "20",
    "nombre_localidad": "Sumapaz",
    "lat": 4.3367,
    "lng": -74.3236,
    "mes": "Ene-Sep (2024vs2025)",
    "tipo": "Hurto de Bicicletas",
    "anio_2018": 0,
    "anio_2019": 0,
    "anio_2020": 0,
    "anio_2021": 0,
    "anio_2022": 0,
    "anio_2023": 0,
    "anio_2024": 0,
    "anio_2025": 0,
    "variacion_porcentaje": 0,
    "total_bogota": 4294
},
{
    "codigo_localidad": "20",
    "nombre_localidad": "Sumapaz",
    "lat": 4.3367,
    "lng": -74.3236,
    "mes": "Ene-Sep (2024vs2025)",
    "tipo": "Hurto a Comercio",
    "anio_2018": 0,
    "anio_2019": 0,
    "anio_2020": 1,
    "anio_2021": 0,
    "anio_2022": 1,
    "anio_2023": 0,
    "anio_2024": 0,
    "anio_2025": 0,
    "variacion_porcentaje": 0,
    "total_bogota": 6694
},
{
    "codigo_localidad": "20",
    "nombre_localidad": "Sumapaz",
    "lat": 4.3367,
    "lng": -74.3236,
    "mes": "Ene-Sep (2024vs2025)",
    "tipo": "Hurto de Celulares",
    "anio_2018": 0,
    "anio_2019": 0,
    "anio_2020": 0,
    "anio_2021": 0,
    "anio_2022": 0,
    "anio_2023": 0,
    "anio_2024": 0,
    "anio_2025": 0,
    "variacion_porcentaje": 0,
    "total_bogota": 24392
},
{
    "codigo_localidad": "20",
    "nombre_localidad": "Sumapaz",
    "lat": 4.3367,
    "lng": -74.3236,
    "mes": "Ene-Sep (2024vs2025)",
    "tipo": "Hurto de Motocicletas",
    "anio_2018": 0,
    "anio_2019": 1,
    "anio_2020": 0,
    "anio_2021": 0,
    "anio_2022": 0,
    "anio_2023": 0,
    "anio_2024": 0,
    "anio_2025": 0,
    "variacion_porcentaje": 0,
    "total_bogota": 3449
},
{
    "codigo_localidad": "20",
    "nombre_localidad": "Sumapaz",
    "lat": 4.3367,
    "lng": -74.3236,
    "mes": "Ene-Sep (2024vs2025)",
    "tipo": "Delitos Sexuales",
    "anio_2018": 8,
    "anio_2019": 6,
    "anio_2020": 14,
    "anio_2021": 0,
    "anio_2022": 0,
    "anio_2023": 0,
    "anio_2024": 0,
    "anio_2025": 0,
    "variacion_porcentaje": 0,
    "total_bogota": 6968
},
{
    "codigo_localidad": "20",
    "nombre_localidad": "Sumapaz",
    "lat": 4.3367,
    "lng": -74.3236,
    "mes": "Ene-Sep (2024vs2025)",
    "tipo": "Violencia Intrafamiliar",
    "anio_2018": 18,
    "anio_2019": 1,
    "anio_2020": 17,
    "anio_2021": 0,
    "anio_2022": 0,
    "anio_2023": 0,
    "anio_2024": 1,
    "anio_2025": 0,
    "variacion_porcentaje": 0,
    "total_bogota": 38257
}
]